{
"meta":{"test_sets":[],"test_metrics":[],"learn_metrics":[{"best_value":"Min","name":"Logloss"}],"launch_mode":"Train","parameters":"","iteration_count":1000,"learn_sets":["learn"],"name":"experiment"},
"iterations":[
{"learn":[0.6682700238],"iteration":0,"passed_time":0.01917524601,"remaining_time":19.15607077},
{"learn":[0.6421474065],"iteration":1,"passed_time":0.03508871867,"remaining_time":17.50927062},
{"learn":[0.6197086636],"iteration":2,"passed_time":0.05045280312,"remaining_time":16.76714824},
{"learn":[0.5975157796],"iteration":3,"passed_time":0.06867645837,"remaining_time":17.10043813},
{"learn":[0.5782594205],"iteration":4,"passed_time":0.08371707593,"remaining_time":16.65969811},
{"learn":[0.5583299206],"iteration":5,"passed_time":0.09793220728,"remaining_time":16.22410234},
{"learn":[0.5410725792],"iteration":6,"passed_time":0.1131197055,"remaining_time":16.04683822},
{"learn":[0.5259757034],"iteration":7,"passed_time":0.1318955074,"remaining_time":16.35504291},
{"learn":[0.5113015989],"iteration":8,"passed_time":0.1486954139,"remaining_time":16.37301724},
{"learn":[0.4986542911],"iteration":9,"passed_time":0.1629743845,"remaining_time":16.13446407},
{"learn":[0.4853494862],"iteration":10,"passed_time":0.1811373105,"remaining_time":16.28589092},
{"learn":[0.4746452443],"iteration":11,"passed_time":0.1961517117,"remaining_time":16.14982427},
{"learn":[0.4635175151],"iteration":12,"passed_time":0.2132473196,"remaining_time":16.19039265},
{"learn":[0.4535648827],"iteration":13,"passed_time":0.2325126156,"remaining_time":16.37553136},
{"learn":[0.4435549023],"iteration":14,"passed_time":0.2475085774,"remaining_time":16.25306325},
{"learn":[0.4344478126],"iteration":15,"passed_time":0.2644128387,"remaining_time":16.26138958},
{"learn":[0.4264927302],"iteration":16,"passed_time":0.2815690795,"remaining_time":16.28131795},
{"learn":[0.4181455909],"iteration":17,"passed_time":0.2982539157,"remaining_time":16.27140807},
{"learn":[0.4098129138],"iteration":18,"passed_time":0.3144060095,"remaining_time":16.2332787},
{"learn":[0.4031679573],"iteration":19,"passed_time":0.3297909571,"remaining_time":16.1597569},
{"learn":[0.3969630625],"iteration":20,"passed_time":0.3445486152,"remaining_time":16.0625283},
{"learn":[0.3905063305],"iteration":21,"passed_time":0.3592295284,"remaining_time":15.9693854},
{"learn":[0.3838255404],"iteration":22,"passed_time":0.3755810081,"remaining_time":15.95402804},
{"learn":[0.3783895453],"iteration":23,"passed_time":0.3961158846,"remaining_time":16.10871264},
{"learn":[0.3729419876],"iteration":24,"passed_time":0.4142279431,"remaining_time":16.15488978},
{"learn":[0.3677615526],"iteration":25,"passed_time":0.4307388568,"remaining_time":16.13614025},
{"learn":[0.3620415025],"iteration":26,"passed_time":0.4461406958,"remaining_time":16.07758878},
{"learn":[0.3582742909],"iteration":27,"passed_time":0.4638175162,"remaining_time":16.10109378},
{"learn":[0.3534669759],"iteration":28,"passed_time":0.4815768843,"remaining_time":16.12452257},
{"learn":[0.3494202197],"iteration":29,"passed_time":0.4984194398,"remaining_time":16.11556189},
{"learn":[0.3453029778],"iteration":30,"passed_time":0.5147797327,"remaining_time":16.0910181},
{"learn":[0.342276529],"iteration":31,"passed_time":0.5307248543,"remaining_time":16.05442684},
{"learn":[0.3394467172],"iteration":32,"passed_time":0.5457962692,"remaining_time":15.99348461},
{"learn":[0.336216794],"iteration":33,"passed_time":0.5623657448,"remaining_time":15.97780322},
{"learn":[0.3329098341],"iteration":34,"passed_time":0.5781425648,"remaining_time":15.94021643},
{"learn":[0.3298723954],"iteration":35,"passed_time":0.5932687124,"remaining_time":15.88641774},
{"learn":[0.327330469],"iteration":36,"passed_time":0.6112066281,"remaining_time":15.90789143},
{"learn":[0.3240363605],"iteration":37,"passed_time":0.6301949102,"remaining_time":15.95388167},
{"learn":[0.3207912948],"iteration":38,"passed_time":0.6488199284,"remaining_time":15.98758849},
{"learn":[0.3181031705],"iteration":39,"passed_time":0.6659105034,"remaining_time":15.98185208},
{"learn":[0.3159565229],"iteration":40,"passed_time":0.6827719302,"remaining_time":15.97020198},
{"learn":[0.3136324259],"iteration":41,"passed_time":0.6985914971,"remaining_time":15.93453939},
{"learn":[0.3111794212],"iteration":42,"passed_time":0.7175035608,"remaining_time":15.96862576},
{"learn":[0.3090339549],"iteration":43,"passed_time":0.7331163607,"remaining_time":15.92861911},
{"learn":[0.3057012206],"iteration":44,"passed_time":0.749096275,"remaining_time":15.89748761},
{"learn":[0.3035755146],"iteration":45,"passed_time":0.7655772984,"remaining_time":15.87740745},
{"learn":[0.3018813863],"iteration":46,"passed_time":0.7833358838,"remaining_time":15.88338505},
{"learn":[0.2992717486],"iteration":47,"passed_time":0.8000500471,"remaining_time":15.86765927},
{"learn":[0.2968930958],"iteration":48,"passed_time":0.8190819042,"remaining_time":15.89687532},
{"learn":[0.2951561533],"iteration":49,"passed_time":0.8381462442,"remaining_time":15.92477864},
{"learn":[0.292894935],"iteration":50,"passed_time":0.8536681914,"remaining_time":15.8849238},
{"learn":[0.2906916912],"iteration":51,"passed_time":0.868564454,"remaining_time":15.83459812},
{"learn":[0.2889412888],"iteration":52,"passed_time":0.8847358994,"remaining_time":15.80839428},
{"learn":[0.2875199214],"iteration":53,"passed_time":0.9010471342,"remaining_time":15.78501091},
{"learn":[0.2861486888],"iteration":54,"passed_time":0.9201189449,"remaining_time":15.80931642},
{"learn":[0.2847465806],"iteration":55,"passed_time":0.9365090397,"remaining_time":15.78686667},
{"learn":[0.283225964],"iteration":56,"passed_time":0.9534276515,"remaining_time":15.77337325},
{"learn":[0.2813369169],"iteration":57,"passed_time":0.9705512946,"remaining_time":15.76309172},
{"learn":[0.2798605284],"iteration":58,"passed_time":0.9873665297,"remaining_time":15.7476594},
{"learn":[0.2784004279],"iteration":59,"passed_time":1.003381585,"remaining_time":15.71964483},
{"learn":[0.2769338658],"iteration":60,"passed_time":1.018214428,"remaining_time":15.67382538},
{"learn":[0.2753974087],"iteration":61,"passed_time":1.035978007,"remaining_time":15.67334468},
{"learn":[0.2740836135],"iteration":62,"passed_time":1.050209015,"remaining_time":15.61977535},
{"learn":[0.2725385291],"iteration":63,"passed_time":1.065339906,"remaining_time":15.58059613},
{"learn":[0.2710331444],"iteration":64,"passed_time":1.081641228,"remaining_time":15.55899305},
{"learn":[0.269976735],"iteration":65,"passed_time":1.097578606,"remaining_time":15.53240027},
{"learn":[0.2684711893],"iteration":66,"passed_time":1.117104933,"remaining_time":15.55610302},
{"learn":[0.2671424485],"iteration":67,"passed_time":1.134009884,"remaining_time":15.54260605},
{"learn":[0.2658644511],"iteration":68,"passed_time":1.15026798,"remaining_time":15.52028246},
{"learn":[0.2647392385],"iteration":69,"passed_time":1.164952435,"remaining_time":15.47722521},
{"learn":[0.2637925313],"iteration":70,"passed_time":1.18060281,"remaining_time":15.44760578},
{"learn":[0.2622334321],"iteration":71,"passed_time":1.196950387,"remaining_time":15.42736055},
{"learn":[0.2612995226],"iteration":72,"passed_time":1.213386118,"remaining_time":15.40834153},
{"learn":[0.2601929785],"iteration":73,"passed_time":1.232339885,"remaining_time":15.42090181},
{"learn":[0.258975354],"iteration":74,"passed_time":1.254802559,"remaining_time":15.47589823},
{"learn":[0.25710417],"iteration":75,"passed_time":1.271154988,"remaining_time":15.45456854},
{"learn":[0.2561690076],"iteration":76,"passed_time":1.288547836,"remaining_time":15.44583964},
{"learn":[0.2553031317],"iteration":77,"passed_time":1.304756461,"remaining_time":15.42289048},
{"learn":[0.2539782751],"iteration":78,"passed_time":1.320911621,"remaining_time":15.39948865},
{"learn":[0.2527988467],"iteration":79,"passed_time":1.337706192,"remaining_time":15.38362121},
{"learn":[0.2517944157],"iteration":80,"passed_time":1.354626389,"remaining_time":15.36915619},
{"learn":[0.2505946185],"iteration":81,"passed_time":1.370952909,"remaining_time":15.34798501},
{"learn":[0.2497515815],"iteration":82,"passed_time":1.386891584,"remaining_time":15.32264557},
{"learn":[0.2487687544],"iteration":83,"passed_time":1.40343201,"remaining_time":15.30409192},
{"learn":[0.2475002255],"iteration":84,"passed_time":1.419741874,"remaining_time":15.2831037},
{"learn":[0.2462010716],"iteration":85,"passed_time":1.435969686,"remaining_time":15.26135224},
{"learn":[0.2450791703],"iteration":86,"passed_time":1.455311143,"remaining_time":15.27240315},
{"learn":[0.2438208079],"iteration":87,"passed_time":1.472243932,"remaining_time":15.25780075},
{"learn":[0.2428450688],"iteration":88,"passed_time":1.488457428,"remaining_time":15.23578334},
{"learn":[0.2419476372],"iteration":89,"passed_time":1.504583049,"remaining_time":15.21300638},
{"learn":[0.2411005373],"iteration":90,"passed_time":1.521572169,"remaining_time":15.19900112},
{"learn":[0.2402916872],"iteration":91,"passed_time":1.538087284,"remaining_time":15.18025276},
{"learn":[0.2393615902],"iteration":92,"passed_time":1.555914194,"remaining_time":15.17434595},
{"learn":[0.2383257466],"iteration":93,"passed_time":1.572387185,"remaining_time":15.15513606},
{"learn":[0.2377181515],"iteration":94,"passed_time":1.588640433,"remaining_time":15.13389044},
{"learn":[0.2369160493],"iteration":95,"passed_time":1.60771747,"remaining_time":15.1393395},
{"learn":[0.2360713299],"iteration":96,"passed_time":1.626322354,"remaining_time":15.13988748},
{"learn":[0.2351910812],"iteration":97,"passed_time":1.641658235,"remaining_time":15.10995641},
{"learn":[0.234309687],"iteration":98,"passed_time":1.661960752,"remaining_time":15.12552159},
{"learn":[0.23362808],"iteration":99,"passed_time":1.677081308,"remaining_time":15.09373177},
{"learn":[0.2328180844],"iteration":100,"passed_time":1.694929348,"remaining_time":15.08654935},
{"learn":[0.2317737389],"iteration":101,"passed_time":1.711118534,"remaining_time":15.06455337},
{"learn":[0.2309263884],"iteration":102,"passed_time":1.726463793,"remaining_time":15.0353206},
{"learn":[0.2303376587],"iteration":103,"passed_time":1.7459303,"remaining_time":15.04186105},
{"learn":[0.2293142548],"iteration":104,"passed_time":1.76525577,"remaining_time":15.04670395},
{"learn":[0.2285509753],"iteration":105,"passed_time":1.782660974,"remaining_time":15.03489539},
{"learn":[0.2279997258],"iteration":106,"passed_time":1.798655614,"remaining_time":15.01120994},
{"learn":[0.2273691306],"iteration":107,"passed_time":1.815612467,"remaining_time":14.99561408},
{"learn":[0.2267903527],"iteration":108,"passed_time":1.831539114,"remaining_time":14.97157202},
{"learn":[0.2259189281],"iteration":109,"passed_time":1.847602836,"remaining_time":14.94878658},
{"learn":[0.2252471118],"iteration":110,"passed_time":1.864626439,"remaining_time":14.93380995},
{"learn":[0.2248030229],"iteration":111,"passed_time":1.880870121,"remaining_time":14.9126131},
{"learn":[0.2241687227],"iteration":112,"passed_time":1.896936894,"remaining_time":14.89011527},
{"learn":[0.2237573171],"iteration":113,"passed_time":1.913305645,"remaining_time":14.87007721},
{"learn":[0.223110595],"iteration":114,"passed_time":1.932681924,"remaining_time":14.87324785},
{"learn":[0.2223256757],"iteration":115,"passed_time":1.950062852,"remaining_time":14.8608238},
{"learn":[0.2217726363],"iteration":116,"passed_time":1.967564226,"remaining_time":14.84922403},
{"learn":[0.2211715206],"iteration":117,"passed_time":1.989502528,"remaining_time":14.87068839},
{"learn":[0.2204190341],"iteration":118,"passed_time":2.007077844,"remaining_time":14.85912252},
{"learn":[0.2197350108],"iteration":119,"passed_time":2.025188801,"remaining_time":14.85138454},
{"learn":[0.2192245707],"iteration":120,"passed_time":2.046941644,"remaining_time":14.86993145},
{"learn":[0.2181888166],"iteration":121,"passed_time":2.066439477,"remaining_time":14.87158902},
{"learn":[0.2176256465],"iteration":122,"passed_time":2.082234221,"remaining_time":14.84649928},
{"learn":[0.2170377938],"iteration":123,"passed_time":2.100592713,"remaining_time":14.8396711},
{"learn":[0.2165314705],"iteration":124,"passed_time":2.118099451,"remaining_time":14.82669615},
{"learn":[0.2161255241],"iteration":125,"passed_time":2.13602039,"remaining_time":14.81652239},
{"learn":[0.2154567685],"iteration":126,"passed_time":2.152323612,"remaining_time":14.79510641},
{"learn":[0.2149592514],"iteration":127,"passed_time":2.166285769,"remaining_time":14.7578218},
{"learn":[0.2145779159],"iteration":128,"passed_time":2.186982316,"remaining_time":14.76636897},
{"learn":[0.2140945032],"iteration":129,"passed_time":2.206572187,"remaining_time":14.76706002},
{"learn":[0.2134113211],"iteration":130,"passed_time":2.222877454,"remaining_time":14.74565273},
{"learn":[0.2130052315],"iteration":131,"passed_time":2.23950084,"remaining_time":14.72641461},
{"learn":[0.2124693929],"iteration":132,"passed_time":2.255025688,"remaining_time":14.70005467},
{"learn":[0.2118680445],"iteration":133,"passed_time":2.273425957,"remaining_time":14.6924394},
{"learn":[0.2110209445],"iteration":134,"passed_time":2.289652917,"remaining_time":14.67073906},
{"learn":[0.2104960601],"iteration":135,"passed_time":2.306012143,"remaining_time":14.6499595},
{"learn":[0.2099597204],"iteration":136,"passed_time":2.323104655,"remaining_time":14.63386363},
{"learn":[0.2092318985],"iteration":137,"passed_time":2.34138419,"remaining_time":14.62516791},
{"learn":[0.2088101116],"iteration":138,"passed_time":2.358343419,"remaining_time":14.608156},
{"learn":[0.2082137032],"iteration":139,"passed_time":2.377021545,"remaining_time":14.60170378},
{"learn":[0.2077656944],"iteration":140,"passed_time":2.395787498,"remaining_time":14.5956132},
{"learn":[0.2073240398],"iteration":141,"passed_time":2.414598119,"remaining_time":14.58961399},
{"learn":[0.2066564476],"iteration":142,"passed_time":2.432769017,"remaining_time":14.57960173},
{"learn":[0.2062695456],"iteration":143,"passed_time":2.454414584,"remaining_time":14.59013114},
{"learn":[0.2058069671],"iteration":144,"passed_time":2.471156581,"remaining_time":14.5713026},
{"learn":[0.2054678551],"iteration":145,"passed_time":2.488699034,"remaining_time":14.55718476},
{"learn":[0.2050630184],"iteration":146,"passed_time":2.505127461,"remaining_time":14.53655595},
{"learn":[0.2046261427],"iteration":147,"passed_time":2.5212739,"remaining_time":14.51436056},
{"learn":[0.2042904672],"iteration":148,"passed_time":2.537408443,"remaining_time":14.49217842},
{"learn":[0.2039603225],"iteration":149,"passed_time":2.553620398,"remaining_time":14.47051559},
{"learn":[0.2036416689],"iteration":150,"passed_time":2.5700173,"remaining_time":14.44996482},
{"learn":[0.2031661674],"iteration":151,"passed_time":2.587550525,"remaining_time":14.43580819},
{"learn":[0.2027048061],"iteration":152,"passed_time":2.605323826,"remaining_time":14.42293647},
{"learn":[0.2022161489],"iteration":153,"passed_time":2.621375292,"remaining_time":14.40054219},
{"learn":[0.2017441915],"iteration":154,"passed_time":2.637346683,"remaining_time":14.37779321},
{"learn":[0.2013243376],"iteration":155,"passed_time":2.653347759,"remaining_time":14.35529172},
{"learn":[0.2009047522],"iteration":156,"passed_time":2.669620368,"remaining_time":14.33433102},
{"learn":[0.2005678954],"iteration":157,"passed_time":2.686520425,"remaining_time":14.31677341},
{"learn":[0.2001239318],"iteration":158,"passed_time":2.704463531,"remaining_time":14.30474107},
{"learn":[0.1999040262],"iteration":159,"passed_time":2.720240586,"remaining_time":14.28126307},
{"learn":[0.199574508],"iteration":160,"passed_time":2.736937606,"remaining_time":14.26267485},
{"learn":[0.1989513229],"iteration":161,"passed_time":2.754928125,"remaining_time":14.25080104},
{"learn":[0.1985782388],"iteration":162,"passed_time":2.771214695,"remaining_time":14.23010245},
{"learn":[0.1982332381],"iteration":163,"passed_time":2.78737071,"remaining_time":14.20879215},
{"learn":[0.1979105751],"iteration":164,"passed_time":2.805148422,"remaining_time":14.1957511},
{"learn":[0.1975475143],"iteration":165,"passed_time":2.820973601,"remaining_time":14.17284327},
{"learn":[0.1972045003],"iteration":166,"passed_time":2.83996912,"remaining_time":14.16583399},
{"learn":[0.1969064841],"iteration":167,"passed_time":2.85613689,"remaining_time":14.14467793},
{"learn":[0.1965574382],"iteration":168,"passed_time":2.872045518,"remaining_time":14.12230666},
{"learn":[0.1960724503],"iteration":169,"passed_time":2.888216453,"remaining_time":14.10129209},
{"learn":[0.1956036431],"iteration":170,"passed_time":2.906413962,"remaining_time":14.09015892},
{"learn":[0.1952642625],"iteration":171,"passed_time":2.925190561,"remaining_time":14.0817313},
{"learn":[0.1950272815],"iteration":172,"passed_time":2.941593206,"remaining_time":14.06183573},
{"learn":[0.1946385],"iteration":173,"passed_time":2.956575228,"remaining_time":14.03523643},
{"learn":[0.1942986005],"iteration":174,"passed_time":2.972873341,"remaining_time":14.01497432},
{"learn":[0.1940747392],"iteration":175,"passed_time":2.988831926,"remaining_time":13.99316765},
{"learn":[0.1936191771],"iteration":176,"passed_time":3.004888665,"remaining_time":13.97188345},
{"learn":[0.1934077378],"iteration":177,"passed_time":3.023530789,"remaining_time":13.96259724},
{"learn":[0.1929974956],"iteration":178,"passed_time":3.04035123,"remaining_time":13.94485117},
{"learn":[0.1926613548],"iteration":179,"passed_time":3.055320335,"remaining_time":13.91868153},
{"learn":[0.1922497165],"iteration":180,"passed_time":3.07064263,"remaining_time":13.89423378},
{"learn":[0.1920659309],"iteration":181,"passed_time":3.089736791,"remaining_time":13.88683898},
{"learn":[0.1917766672],"iteration":182,"passed_time":3.105346919,"remaining_time":13.86376193},
{"learn":[0.1913244879],"iteration":183,"passed_time":3.121958147,"remaining_time":13.8452057},
{"learn":[0.1909969207],"iteration":184,"passed_time":3.1366689,"remaining_time":13.81829813},
{"learn":[0.1904556767],"iteration":185,"passed_time":3.15250474,"remaining_time":13.79644548},
{"learn":[0.1902560684],"iteration":186,"passed_time":3.175418346,"remaining_time":13.80542842},
{"learn":[0.1899615425],"iteration":187,"passed_time":3.193890474,"remaining_time":13.79488864},
{"learn":[0.1896577807],"iteration":188,"passed_time":3.211407096,"remaining_time":13.78016484},
{"learn":[0.1891921594],"iteration":189,"passed_time":3.22902462,"remaining_time":13.7658418},
{"learn":[0.1888135625],"iteration":190,"passed_time":3.249368891,"remaining_time":13.76303368},
{"learn":[0.1883987919],"iteration":191,"passed_time":3.267451828,"remaining_time":13.75052644},
{"learn":[0.1878982857],"iteration":192,"passed_time":3.28494127,"remaining_time":13.73547982},
{"learn":[0.1874484333],"iteration":193,"passed_time":3.301005772,"remaining_time":13.7144879},
{"learn":[0.1870523134],"iteration":194,"passed_time":3.317088516,"remaining_time":13.69362182},
{"learn":[0.1867713727],"iteration":195,"passed_time":3.337810603,"remaining_time":13.69183533},
{"learn":[0.1864542763],"iteration":196,"passed_time":3.352383149,"remaining_time":13.6647902},
{"learn":[0.1862955848],"iteration":197,"passed_time":3.367177563,"remaining_time":13.63876973},
{"learn":[0.1859708277],"iteration":198,"passed_time":3.383969684,"remaining_time":13.6209031},
{"learn":[0.1857771261],"iteration":199,"passed_time":3.399782733,"remaining_time":13.59913093},
{"learn":[0.1855073364],"iteration":200,"passed_time":3.415438478,"remaining_time":13.57679275},
{"learn":[0.1852213303],"iteration":201,"passed_time":3.43542259,"remaining_time":13.57161993},
{"learn":[0.1848261948],"iteration":202,"passed_time":3.451941261,"remaining_time":13.55269549},
{"learn":[0.1845527358],"iteration":203,"passed_time":3.466666491,"remaining_time":13.5267967},
{"learn":[0.1842463429],"iteration":204,"passed_time":3.481765433,"remaining_time":13.50245619},
{"learn":[0.1840241463],"iteration":205,"passed_time":3.497778892,"remaining_time":13.48173029},
{"learn":[0.1837314281],"iteration":206,"passed_time":3.513837027,"remaining_time":13.46122107},
{"learn":[0.1834720377],"iteration":207,"passed_time":3.530092991,"remaining_time":13.44150793},
{"learn":[0.1831265357],"iteration":208,"passed_time":3.548524773,"remaining_time":13.43006266},
{"learn":[0.1828830395],"iteration":209,"passed_time":3.564053899,"remaining_time":13.40763133},
{"learn":[0.1826894631],"iteration":210,"passed_time":3.579983406,"remaining_time":13.38676259},
{"learn":[0.1824073411],"iteration":211,"passed_time":3.599102875,"remaining_time":13.37779748},
{"learn":[0.1821488456],"iteration":212,"passed_time":3.61437993,"remaining_time":13.35453993},
{"learn":[0.1819867534],"iteration":213,"passed_time":3.634698296,"remaining_time":13.34987318},
{"learn":[0.1816351479],"iteration":214,"passed_time":3.651601183,"remaining_time":13.33259036},
{"learn":[0.1814255521],"iteration":215,"passed_time":3.667971673,"remaining_time":13.31337867},
{"learn":[0.1812488545],"iteration":216,"passed_time":3.683364428,"remaining_time":13.29066519},
{"learn":[0.18094239],"iteration":217,"passed_time":3.698774098,"remaining_time":13.26807956},
{"learn":[0.1806218749],"iteration":218,"passed_time":3.713357971,"remaining_time":13.2426145},
{"learn":[0.1804101312],"iteration":219,"passed_time":3.728335536,"remaining_time":13.21864417},
{"learn":[0.1800402331],"iteration":220,"passed_time":3.746986716,"remaining_time":13.20770431},
{"learn":[0.1798183766],"iteration":221,"passed_time":3.763725758,"remaining_time":13.18999387},
{"learn":[0.1795807511],"iteration":222,"passed_time":3.78095383,"remaining_time":13.17399608},
{"learn":[0.1794191959],"iteration":223,"passed_time":3.795767482,"remaining_time":13.14962306},
{"learn":[0.1791363579],"iteration":224,"passed_time":3.810521543,"remaining_time":13.12512976},
{"learn":[0.1788626483],"iteration":225,"passed_time":3.826277817,"remaining_time":13.104155},
{"learn":[0.1786385545],"iteration":226,"passed_time":3.842670546,"remaining_time":13.08539353},
{"learn":[0.178329065],"iteration":227,"passed_time":3.860905443,"remaining_time":13.07289036},
{"learn":[0.1780475695],"iteration":228,"passed_time":3.8759802,"remaining_time":13.04969753},
{"learn":[0.1778098366],"iteration":229,"passed_time":3.891846352,"remaining_time":13.02922474},
{"learn":[0.1774582312],"iteration":230,"passed_time":3.907854275,"remaining_time":13.0092638},
{"learn":[0.1772020983],"iteration":231,"passed_time":3.927785787,"remaining_time":13.00232536},
{"learn":[0.176956132],"iteration":232,"passed_time":3.947391889,"remaining_time":12.9942042},
{"learn":[0.1767342218],"iteration":233,"passed_time":3.967089812,"remaining_time":12.98628545},
{"learn":[0.1764735784],"iteration":234,"passed_time":3.983763888,"remaining_time":12.96842287},
{"learn":[0.1761634625],"iteration":235,"passed_time":3.999714848,"remaining_time":12.94822942},
{"learn":[0.1759535445],"iteration":236,"passed_time":4.016022756,"remaining_time":12.92922094},
{"learn":[0.1757376125],"iteration":237,"passed_time":4.033667258,"remaining_time":12.9145145},
{"learn":[0.1756064854],"iteration":238,"passed_time":4.049976766,"remaining_time":12.89553272},
{"learn":[0.1754056601],"iteration":239,"passed_time":4.067061664,"remaining_time":12.8790286},
{"learn":[0.1750125292],"iteration":240,"passed_time":4.084464661,"remaining_time":12.86352148},
{"learn":[0.1748960791],"iteration":241,"passed_time":4.101977534,"remaining_time":12.84834285},
{"learn":[0.1744658439],"iteration":242,"passed_time":4.118150778,"remaining_time":12.82897177},
{"learn":[0.1743074568],"iteration":243,"passed_time":4.134667202,"remaining_time":12.81069018},
{"learn":[0.1741565693],"iteration":244,"passed_time":4.151780881,"remaining_time":12.79426353},
{"learn":[0.1739506249],"iteration":245,"passed_time":4.169680855,"remaining_time":12.78024132},
{"learn":[0.1736348351],"iteration":246,"passed_time":4.185451965,"remaining_time":12.75969769},
{"learn":[0.1734303405],"iteration":247,"passed_time":4.201816763,"remaining_time":12.74099277},
{"learn":[0.1731914621],"iteration":248,"passed_time":4.217841435,"remaining_time":12.7212808},
{"learn":[0.1729931068],"iteration":249,"passed_time":4.234948975,"remaining_time":12.70484693},
{"learn":[0.1727404821],"iteration":250,"passed_time":4.253710201,"remaining_time":12.69334239},
{"learn":[0.1725113765],"iteration":251,"passed_time":4.273116018,"remaining_time":12.68369358},
{"learn":[0.1723527567],"iteration":252,"passed_time":4.288538321,"remaining_time":12.66220603},
{"learn":[0.1721481547],"iteration":253,"passed_time":4.303330679,"remaining_time":12.63891609},
{"learn":[0.1719129277],"iteration":254,"passed_time":4.319489445,"remaining_time":12.61968485},
{"learn":[0.1716092733],"iteration":255,"passed_time":4.335536134,"remaining_time":12.60015189},
{"learn":[0.171350205],"iteration":256,"passed_time":4.352062162,"remaining_time":12.58203185},
{"learn":[0.1710899912],"iteration":257,"passed_time":4.370115558,"remaining_time":12.56831684},
{"learn":[0.1708490903],"iteration":258,"passed_time":4.38554151,"remaining_time":12.54705119},
{"learn":[0.170731441],"iteration":259,"passed_time":4.401499218,"remaining_time":12.52734393},
{"learn":[0.1705116071],"iteration":260,"passed_time":4.423307997,"remaining_time":12.52423222},
{"learn":[0.170364353],"iteration":261,"passed_time":4.439473354,"remaining_time":12.50508143},
{"learn":[0.1702082928],"iteration":262,"passed_time":4.455728113,"remaining_time":12.48620388},
{"learn":[0.170075143],"iteration":263,"passed_time":4.471269427,"remaining_time":12.46535719},
{"learn":[0.1699579054],"iteration":264,"passed_time":4.48865051,"remaining_time":12.4496533},
{"learn":[0.1697421882],"iteration":265,"passed_time":4.504237867,"remaining_time":12.4289872},
{"learn":[0.1693774092],"iteration":266,"passed_time":4.519905282,"remaining_time":12.40857892},
{"learn":[0.1692175902],"iteration":267,"passed_time":4.536078958,"remaining_time":12.3895888},
{"learn":[0.1689966823],"iteration":268,"passed_time":4.552688518,"remaining_time":12.37180411},
{"learn":[0.168686101],"iteration":269,"passed_time":4.567804786,"remaining_time":12.34999072},
{"learn":[0.1684597877],"iteration":270,"passed_time":4.586855719,"remaining_time":12.33881114},
{"learn":[0.1683497454],"iteration":271,"passed_time":4.602715237,"remaining_time":12.31903196},
{"learn":[0.1682187078],"iteration":272,"passed_time":4.617260113,"remaining_time":12.29578059},
{"learn":[0.1680298031],"iteration":273,"passed_time":4.632164969,"remaining_time":12.2735466},
{"learn":[0.1678120275],"iteration":274,"passed_time":4.64887293,"remaining_time":12.25611954},
{"learn":[0.1675859647],"iteration":275,"passed_time":4.664032488,"remaining_time":12.23463595},
{"learn":[0.1673447774],"iteration":276,"passed_time":4.683100899,"remaining_time":12.22340054},
{"learn":[0.1671209878],"iteration":277,"passed_time":4.69768924,"remaining_time":12.2004735},
{"learn":[0.1669204846],"iteration":278,"passed_time":4.720067346,"remaining_time":12.19773676},
{"learn":[0.1668331381],"iteration":279,"passed_time":4.744272634,"remaining_time":12.1995582},
{"learn":[0.1666313104],"iteration":280,"passed_time":4.767514684,"remaining_time":12.19872974},
{"learn":[0.1664913054],"iteration":281,"passed_time":4.785472398,"remaining_time":12.18428788},
{"learn":[0.1663148226],"iteration":282,"passed_time":4.810753085,"remaining_time":12.18837442},
{"learn":[0.166113317],"iteration":283,"passed_time":4.839273789,"remaining_time":12.20042265},
{"learn":[0.1658758348],"iteration":284,"passed_time":4.865705542,"remaining_time":12.20694548},
{"learn":[0.1656643954],"iteration":285,"passed_time":4.886017866,"remaining_time":12.19796069},
{"learn":[0.1654163707],"iteration":286,"passed_time":4.90751072,"remaining_time":12.19182977},
{"learn":[0.165263049],"iteration":287,"passed_time":4.924507081,"remaining_time":12.17447584},
{"learn":[0.165080749],"iteration":288,"passed_time":4.940721329,"remaining_time":12.15520022},
{"learn":[0.1648880855],"iteration":289,"passed_time":4.957238818,"remaining_time":12.13668814},
{"learn":[0.1646167923],"iteration":290,"passed_time":4.973054287,"remaining_time":12.11647935},
{"learn":[0.1644963329],"iteration":291,"passed_time":4.989314473,"remaining_time":12.09737893},
{"learn":[0.1643634874],"iteration":292,"passed_time":5.006252769,"remaining_time":12.07993416},
{"learn":[0.1642468584],"iteration":293,"passed_time":5.022212513,"remaining_time":12.06014297},
{"learn":[0.1640082664],"iteration":294,"passed_time":5.038117055,"remaining_time":12.04024584},
{"learn":[0.1637596869],"iteration":295,"passed_time":5.055745527,"remaining_time":12.02447585},
{"learn":[0.1635896834],"iteration":296,"passed_time":5.072578112,"remaining_time":12.00680947},
{"learn":[0.1634067927],"iteration":297,"passed_time":5.088712258,"remaining_time":11.98750337},
{"learn":[0.1633037847],"iteration":298,"passed_time":5.107307071,"remaining_time":11.97398748},
{"learn":[0.1631233282],"iteration":299,"passed_time":5.124680242,"remaining_time":11.95758723},
{"learn":[0.1629680555],"iteration":300,"passed_time":5.141099461,"remaining_time":11.93896519},
{"learn":[0.1628007011],"iteration":301,"passed_time":5.156922883,"remaining_time":11.9189807},
{"learn":[0.1626740486],"iteration":302,"passed_time":5.172996049,"remaining_time":11.89959817},
{"learn":[0.1625077144],"iteration":303,"passed_time":5.189018215,"remaining_time":11.88012065},
{"learn":[0.1623609079],"iteration":304,"passed_time":5.205596794,"remaining_time":11.86193368},
{"learn":[0.1620467826],"iteration":305,"passed_time":5.230198091,"remaining_time":11.86195253},
{"learn":[0.1618602048],"iteration":306,"passed_time":5.245865148,"remaining_time":11.84164348},
{"learn":[0.1617157788],"iteration":307,"passed_time":5.261202727,"remaining_time":11.82062431},
{"learn":[0.1615442718],"iteration":308,"passed_time":5.276138593,"remaining_time":11.79874358},
{"learn":[0.1613354635],"iteration":309,"passed_time":5.290521896,"remaining_time":11.77567777},
{"learn":[0.1612517326],"iteration":310,"passed_time":5.306081069,"remaining_time":11.75527285},
{"learn":[0.1610526792],"iteration":311,"passed_time":5.325374999,"remaining_time":11.74313461},
{"learn":[0.1608605527],"iteration":312,"passed_time":5.34003832,"remaining_time":11.72078698},
{"learn":[0.1606777158],"iteration":313,"passed_time":5.355972451,"remaining_time":11.70126465},
{"learn":[0.1604550359],"iteration":314,"passed_time":5.371490338,"remaining_time":11.68085994},
{"learn":[0.1602003349],"iteration":315,"passed_time":5.390882343,"remaining_time":11.66887191},
{"learn":[0.1599921352],"iteration":316,"passed_time":5.408973481,"remaining_time":11.65403434},
{"learn":[0.159826517],"iteration":317,"passed_time":5.423625634,"remaining_time":11.63180089},
{"learn":[0.15965501],"iteration":318,"passed_time":5.442898551,"remaining_time":11.61947935},
{"learn":[0.1595548658],"iteration":319,"passed_time":5.458526084,"remaining_time":11.59936793},
{"learn":[0.1593953689],"iteration":320,"passed_time":5.474292896,"remaining_time":11.57957906},
{"learn":[0.1592357826],"iteration":321,"passed_time":5.489541038,"remaining_time":11.55872306},
{"learn":[0.1590187587],"iteration":322,"passed_time":5.50394424,"remaining_time":11.53613081},
{"learn":[0.1588046345],"iteration":323,"passed_time":5.519731079,"remaining_time":11.51647596},
{"learn":[0.1586356334],"iteration":324,"passed_time":5.538229287,"remaining_time":11.50247621},
{"learn":[0.1584720914],"iteration":325,"passed_time":5.555785479,"remaining_time":11.48650127},
{"learn":[0.1582936933],"iteration":326,"passed_time":5.571446736,"remaining_time":11.46661668},
{"learn":[0.1581908822],"iteration":327,"passed_time":5.585758067,"remaining_time":11.44399214},
{"learn":[0.157929666],"iteration":328,"passed_time":5.60113249,"remaining_time":11.42358632},
{"learn":[0.157806665],"iteration":329,"passed_time":5.621921504,"remaining_time":11.41420427},
{"learn":[0.1576457362],"iteration":330,"passed_time":5.638024024,"remaining_time":11.39528118},
{"learn":[0.1575541119],"iteration":331,"passed_time":5.655512552,"remaining_time":11.37916381},
{"learn":[0.157354969],"iteration":332,"passed_time":5.670916846,"remaining_time":11.35886347},
{"learn":[0.15713603],"iteration":333,"passed_time":5.686161657,"remaining_time":11.33827444},
{"learn":[0.1570389465],"iteration":334,"passed_time":5.700574549,"remaining_time":11.3160659},
{"learn":[0.1567651654],"iteration":335,"passed_time":5.723282293,"remaining_time":11.31029596},
{"learn":[0.1566847994],"iteration":336,"passed_time":5.743276861,"remaining_time":11.29908771},
{"learn":[0.1564747024],"iteration":337,"passed_time":5.758938134,"remaining_time":11.27934037},
{"learn":[0.1564048074],"iteration":338,"passed_time":5.775135819,"remaining_time":11.26066306},
{"learn":[0.1562928141],"iteration":339,"passed_time":5.790882651,"remaining_time":11.24112515},
{"learn":[0.1562165291],"iteration":340,"passed_time":5.806729909,"remaining_time":11.22180355},
{"learn":[0.1560866012],"iteration":341,"passed_time":5.82264949,"remaining_time":11.20264142},
{"learn":[0.1559231666],"iteration":342,"passed_time":5.838756913,"remaining_time":11.18385799},
{"learn":[0.1557712231],"iteration":343,"passed_time":5.856484541,"remaining_time":11.16817982},
{"learn":[0.1556138204],"iteration":344,"passed_time":5.873164237,"remaining_time":11.15050022},
{"learn":[0.1554840535],"iteration":345,"passed_time":5.88954778,"remaining_time":11.13226661},
{"learn":[0.1552870764],"iteration":346,"passed_time":5.906819586,"remaining_time":11.11571524},
{"learn":[0.155052637],"iteration":347,"passed_time":5.936241465,"remaining_time":11.12192366},
{"learn":[0.1549163013],"iteration":348,"passed_time":5.950754869,"remaining_time":11.10011868},
{"learn":[0.1547892014],"iteration":349,"passed_time":5.968273061,"remaining_time":11.08393568},
{"learn":[0.1546963062],"iteration":350,"passed_time":5.983545224,"remaining_time":11.06359217},
{"learn":[0.154614043],"iteration":351,"passed_time":5.998375067,"remaining_time":11.04246319},
{"learn":[0.1543962853],"iteration":352,"passed_time":6.013132842,"remaining_time":11.02123782},
{"learn":[0.1542729979],"iteration":353,"passed_time":6.034192964,"remaining_time":11.01154987},
{"learn":[0.1541052497],"iteration":354,"passed_time":6.051438325,"remaining_time":10.99486682},
{"learn":[0.1539152352],"iteration":355,"passed_time":6.067409252,"remaining_time":10.97587516},
{"learn":[0.1537857906],"iteration":356,"passed_time":6.082757465,"remaining_time":10.95577885},
{"learn":[0.1536330774],"iteration":357,"passed_time":6.098428496,"remaining_time":10.93628797},
{"learn":[0.1535413278],"iteration":358,"passed_time":6.112152345,"remaining_time":10.91334165},
{"learn":[0.1533828154],"iteration":359,"passed_time":6.127261105,"remaining_time":10.89290863},
{"learn":[0.1532901171],"iteration":360,"passed_time":6.143627588,"remaining_time":10.87473138},
{"learn":[0.1532107356],"iteration":361,"passed_time":6.161190904,"remaining_time":10.85867347},
{"learn":[0.1530202558],"iteration":362,"passed_time":6.176064642,"remaining_time":10.83788754},
{"learn":[0.1528434686],"iteration":363,"passed_time":6.192197991,"remaining_time":10.81933495},
{"learn":[0.1526346246],"iteration":364,"passed_time":6.211356389,"remaining_time":10.80605837},
{"learn":[0.1525102453],"iteration":365,"passed_time":6.22681042,"remaining_time":10.7863328},
{"learn":[0.1523924707],"iteration":366,"passed_time":6.241935222,"remaining_time":10.76606266},
{"learn":[0.1522469529],"iteration":367,"passed_time":6.258259955,"remaining_time":10.74788123},
{"learn":[0.1521157542],"iteration":368,"passed_time":6.276823992,"remaining_time":10.73353913},
{"learn":[0.1519910169],"iteration":369,"passed_time":6.290950936,"remaining_time":10.71161916},
{"learn":[0.1518391092],"iteration":370,"passed_time":6.307347987,"remaining_time":10.69358998},
{"learn":[0.1516487905],"iteration":371,"passed_time":6.324459716,"remaining_time":10.67677608},
{"learn":[0.1514293861],"iteration":372,"passed_time":6.340178833,"remaining_time":10.65761965},
{"learn":[0.1511978463],"iteration":373,"passed_time":6.355952525,"remaining_time":10.63857294},
{"learn":[0.1510788367],"iteration":374,"passed_time":6.37727312,"remaining_time":10.62878853},
{"learn":[0.1509416239],"iteration":375,"passed_time":6.393654337,"remaining_time":10.61074549},
{"learn":[0.1508297201],"iteration":376,"passed_time":6.410180035,"remaining_time":10.59295003},
{"learn":[0.1506745727],"iteration":377,"passed_time":6.428064622,"remaining_time":10.57739734},
{"learn":[0.1504988774],"iteration":378,"passed_time":6.443222281,"remaining_time":10.55736421},
{"learn":[0.150406734],"iteration":379,"passed_time":6.458137609,"remaining_time":10.53696136},
{"learn":[0.1501687148],"iteration":380,"passed_time":6.475980939,"remaining_time":10.52134436},
{"learn":[0.1500022105],"iteration":381,"passed_time":6.490663293,"remaining_time":10.50060187},
{"learn":[0.1498299876],"iteration":382,"passed_time":6.505177943,"remaining_time":10.47962086},
{"learn":[0.1497082484],"iteration":383,"passed_time":6.521266386,"remaining_time":10.46119816},
{"learn":[0.1495163188],"iteration":384,"passed_time":6.539695213,"remaining_time":10.44652612},
{"learn":[0.1493999582],"iteration":385,"passed_time":6.557024153,"remaining_time":10.43008505},
{"learn":[0.1492735384],"iteration":386,"passed_time":6.571686783,"remaining_time":10.40941602},
{"learn":[0.1490928404],"iteration":387,"passed_time":6.590014016,"remaining_time":10.39455819},
{"learn":[0.1488833967],"iteration":388,"passed_time":6.60478671,"remaining_time":10.37409943},
{"learn":[0.1487002018],"iteration":389,"passed_time":6.622867047,"remaining_time":10.35884333},
{"learn":[0.1485552835],"iteration":390,"passed_time":6.637151571,"remaining_time":10.33766063},
{"learn":[0.1484257941],"iteration":391,"passed_time":6.651664187,"remaining_time":10.3168669},
{"learn":[0.1483228219],"iteration":392,"passed_time":6.667956047,"remaining_time":10.29885323},
{"learn":[0.1481894306],"iteration":393,"passed_time":6.686678423,"remaining_time":10.28458661},
{"learn":[0.1480174314],"iteration":394,"passed_time":6.703835866,"remaining_time":10.2679005},
{"learn":[0.1478407426],"iteration":395,"passed_time":6.718923101,"remaining_time":10.24805443},
{"learn":[0.1476913228],"iteration":396,"passed_time":6.733889517,"remaining_time":10.22804881},
{"learn":[0.1475212925],"iteration":397,"passed_time":6.749137195,"remaining_time":10.20849395},
{"learn":[0.1474275024],"iteration":398,"passed_time":6.764894471,"remaining_time":10.18972826},
{"learn":[0.1473146321],"iteration":399,"passed_time":6.780951057,"remaining_time":10.17142659},
{"learn":[0.1471421586],"iteration":400,"passed_time":6.799020619,"remaining_time":10.15614302},
{"learn":[0.1470284202],"iteration":401,"passed_time":6.816884487,"remaining_time":10.14053961},
{"learn":[0.1468611552],"iteration":402,"passed_time":6.832154816,"remaining_time":10.12108294},
{"learn":[0.1467544869],"iteration":403,"passed_time":6.847756873,"remaining_time":10.10213638},
{"learn":[0.1466183391],"iteration":404,"passed_time":6.865816098,"remaining_time":10.08681624},
{"learn":[0.1464989715],"iteration":405,"passed_time":6.882716881,"remaining_time":10.06978775},
{"learn":[0.1463029341],"iteration":406,"passed_time":6.899460156,"remaining_time":10.0525304},
{"learn":[0.1462005884],"iteration":407,"passed_time":6.916613761,"remaining_time":10.03587095},
{"learn":[0.1460935889],"iteration":408,"passed_time":6.930513268,"remaining_time":10.01450695},
{"learn":[0.1459840657],"iteration":409,"passed_time":6.947238159,"remaining_time":9.997245155},
{"learn":[0.1457980248],"iteration":410,"passed_time":6.962419055,"remaining_time":9.977773293},
{"learn":[0.1456996884],"iteration":411,"passed_time":6.977578103,"remaining_time":9.958291079},
{"learn":[0.1455242258],"iteration":412,"passed_time":6.995790865,"remaining_time":9.943170067},
{"learn":[0.1453527904],"iteration":413,"passed_time":7.011629691,"remaining_time":9.924673911},
{"learn":[0.1451546319],"iteration":414,"passed_time":7.029757265,"remaining_time":9.909416868},
{"learn":[0.145037099],"iteration":415,"passed_time":7.045948896,"remaining_time":9.891428258},
{"learn":[0.1449430404],"iteration":416,"passed_time":7.060563983,"remaining_time":9.871244129},
{"learn":[0.1448479706],"iteration":417,"passed_time":7.076031103,"remaining_time":9.852272971},
{"learn":[0.144760463],"iteration":418,"passed_time":7.092073782,"remaining_time":9.834116629},
{"learn":[0.1446115354],"iteration":419,"passed_time":7.110154353,"remaining_time":9.818784582},
{"learn":[0.1444598782],"iteration":420,"passed_time":7.125639048,"remaining_time":9.79986938},
{"learn":[0.1443291001],"iteration":421,"passed_time":7.141281492,"remaining_time":9.781186498},
{"learn":[0.1442141894],"iteration":422,"passed_time":7.157000659,"remaining_time":9.762622648},
{"learn":[0.1440025889],"iteration":423,"passed_time":7.172940277,"remaining_time":9.744371697},
{"learn":[0.1438656894],"iteration":424,"passed_time":7.190967644,"remaining_time":9.728956224},
{"learn":[0.1437058972],"iteration":425,"passed_time":7.21315409,"remaining_time":9.719132506},
{"learn":[0.1436246094],"iteration":426,"passed_time":7.22767861,"remaining_time":9.698969189},
{"learn":[0.1434746258],"iteration":427,"passed_time":7.243932976,"remaining_time":9.68114407},
{"learn":[0.1433643688],"iteration":428,"passed_time":7.258463242,"remaining_time":9.661031494},
{"learn":[0.1432506662],"iteration":429,"passed_time":7.274099743,"remaining_time":9.642411288},
{"learn":[0.1431530189],"iteration":430,"passed_time":7.290111946,"remaining_time":9.624300921},
{"learn":[0.1429800084],"iteration":431,"passed_time":7.308077219,"remaining_time":9.608768195},
{"learn":[0.1428633614],"iteration":432,"passed_time":7.323694309,"remaining_time":9.59014936},
{"learn":[0.1427007412],"iteration":433,"passed_time":7.339317004,"remaining_time":9.571551669},
{"learn":[0.1426242414],"iteration":434,"passed_time":7.358580049,"remaining_time":9.557695926},
{"learn":[0.1424872166],"iteration":435,"passed_time":7.37518643,"remaining_time":9.540378777},
{"learn":[0.1424002013],"iteration":436,"passed_time":7.389697996,"remaining_time":9.520366068},
{"learn":[0.1422924769],"iteration":437,"passed_time":7.405931689,"remaining_time":9.502588149},
{"learn":[0.1421247287],"iteration":438,"passed_time":7.424189485,"remaining_time":9.487403875},
{"learn":[0.1419896727],"iteration":439,"passed_time":7.43886743,"remaining_time":9.467649456},
{"learn":[0.1418818588],"iteration":440,"passed_time":7.454682068,"remaining_time":9.449358903},
{"learn":[0.1418370222],"iteration":441,"passed_time":7.470250015,"remaining_time":9.430768119},
{"learn":[0.1416327781],"iteration":442,"passed_time":7.48650115,"remaining_time":9.413049979},
{"learn":[0.1414633832],"iteration":443,"passed_time":7.50490409,"remaining_time":9.39803305},
{"learn":[0.1412682676],"iteration":444,"passed_time":7.524233502,"remaining_time":9.38415639},
{"learn":[0.1411622884],"iteration":445,"passed_time":7.540663545,"remaining_time":9.366653821},
{"learn":[0.1410217196],"iteration":446,"passed_time":7.554689913,"remaining_time":9.346182375},
{"learn":[0.1409530147],"iteration":447,"passed_time":7.57010177,"remaining_time":9.327446823},
{"learn":[0.1408822068],"iteration":448,"passed_time":7.586647942,"remaining_time":9.310118076},
{"learn":[0.1407717708],"iteration":449,"passed_time":7.60247282,"remaining_time":9.291911225},
{"learn":[0.1406914585],"iteration":450,"passed_time":7.626337929,"remaining_time":9.283502269},
{"learn":[0.14063633],"iteration":451,"passed_time":7.641590592,"remaining_time":9.264583285},
{"learn":[0.1404665413],"iteration":452,"passed_time":7.656849824,"remaining_time":9.245688418},
{"learn":[0.1403294001],"iteration":453,"passed_time":7.67171111,"remaining_time":9.226330983},
{"learn":[0.1401929302],"iteration":454,"passed_time":7.68951721,"remaining_time":9.210520614},
{"learn":[0.1401014759],"iteration":455,"passed_time":7.705864032,"remaining_time":9.192960599},
{"learn":[0.1399291903],"iteration":456,"passed_time":7.720300098,"remaining_time":9.173135565},
{"learn":[0.1397492976],"iteration":457,"passed_time":7.73824917,"remaining_time":9.157491375},
{"learn":[0.1396245425],"iteration":458,"passed_time":7.754250658,"remaining_time":9.139541625},
{"learn":[0.1394710239],"iteration":459,"passed_time":7.768594506,"remaining_time":9.11965442},
{"learn":[0.1393812879],"iteration":460,"passed_time":7.784143819,"remaining_time":9.101200691},
{"learn":[0.1393110079],"iteration":461,"passed_time":7.800320822,"remaining_time":9.083490481},
{"learn":[0.1392270891],"iteration":462,"passed_time":7.817234744,"remaining_time":9.066641592},
{"learn":[0.1390661693],"iteration":463,"passed_time":7.83573616,"remaining_time":9.051626254},
{"learn":[0.138855947],"iteration":464,"passed_time":7.852856134,"remaining_time":9.035006519},
{"learn":[0.1387576911],"iteration":465,"passed_time":7.870408062,"remaining_time":9.018879624},
{"learn":[0.1386395496],"iteration":466,"passed_time":7.885638078,"remaining_time":9.000096564},
{"learn":[0.138569037],"iteration":467,"passed_time":7.899781615,"remaining_time":8.98009363},
{"learn":[0.1384574107],"iteration":468,"passed_time":7.916223223,"remaining_time":8.962717551},
{"learn":[0.1382600756],"iteration":469,"passed_time":7.934966889,"remaining_time":8.947941385},
{"learn":[0.1381455676],"iteration":470,"passed_time":7.950118556,"remaining_time":8.929114047},
{"learn":[0.1379157729],"iteration":471,"passed_time":7.964756806,"remaining_time":8.909727953},
{"learn":[0.1377356297],"iteration":472,"passed_time":7.98074822,"remaining_time":8.891869581},
{"learn":[0.1375958216],"iteration":473,"passed_time":7.99712946,"remaining_time":8.874451679},
{"learn":[0.1374138885],"iteration":474,"passed_time":8.019055745,"remaining_time":8.863166876},
{"learn":[0.1372419341],"iteration":475,"passed_time":8.036055956,"remaining_time":8.846414539},
{"learn":[0.1371454681],"iteration":476,"passed_time":8.051445198,"remaining_time":8.827894839},
{"learn":[0.1370642519],"iteration":477,"passed_time":8.067127887,"remaining_time":8.809708697},
{"learn":[0.1369084423],"iteration":478,"passed_time":8.082304065,"remaining_time":8.790982084},
{"learn":[0.136763533],"iteration":479,"passed_time":8.097487556,"remaining_time":8.772278185},
{"learn":[0.1366003669],"iteration":480,"passed_time":8.114706467,"remaining_time":8.755785148},
{"learn":[0.1363786535],"iteration":481,"passed_time":8.130848763,"remaining_time":8.738132073},
{"learn":[0.136225994],"iteration":482,"passed_time":8.150046645,"remaining_time":8.723755932},
{"learn":[0.1361661044],"iteration":483,"passed_time":8.16465356,"remaining_time":8.704465366},
{"learn":[0.1360012021],"iteration":484,"passed_time":8.18217053,"remaining_time":8.688284171},
{"learn":[0.1359434066],"iteration":485,"passed_time":8.199015683,"remaining_time":8.671386957},
{"learn":[0.1358772882],"iteration":486,"passed_time":8.214173701,"remaining_time":8.652712748},
{"learn":[0.1357877401],"iteration":487,"passed_time":8.229547059,"remaining_time":8.634278881},
{"learn":[0.1357065598],"iteration":488,"passed_time":8.247276041,"remaining_time":8.618319135},
{"learn":[0.1355973767],"iteration":489,"passed_time":8.262496221,"remaining_time":8.599740964},
{"learn":[0.1354798437],"iteration":490,"passed_time":8.277621204,"remaining_time":8.581077786},
{"learn":[0.135387396],"iteration":491,"passed_time":8.293154836,"remaining_time":8.562850928},
{"learn":[0.1352728343],"iteration":492,"passed_time":8.309718772,"remaining_time":8.545694559},
{"learn":[0.1351803419],"iteration":493,"passed_time":8.326016439,"remaining_time":8.52826785},
{"learn":[0.1350953222],"iteration":494,"passed_time":8.342119839,"remaining_time":8.510647512},
{"learn":[0.1349416783],"iteration":495,"passed_time":8.362257778,"remaining_time":8.497132903},
{"learn":[0.134851298],"iteration":496,"passed_time":8.378541283,"remaining_time":8.479690675},
{"learn":[0.134707221],"iteration":497,"passed_time":8.395886377,"remaining_time":8.463323215},
{"learn":[0.1346014744],"iteration":498,"passed_time":8.413625528,"remaining_time":8.447347474},
{"learn":[0.1345152914],"iteration":499,"passed_time":8.429057157,"remaining_time":8.429057157},
{"learn":[0.1343804771],"iteration":500,"passed_time":8.444163424,"remaining_time":8.410454189},
{"learn":[0.1342307351],"iteration":501,"passed_time":8.46225499,"remaining_time":8.394826663},
{"learn":[0.134101362],"iteration":502,"passed_time":8.477767253,"remaining_time":8.376640805},
{"learn":[0.1339818871],"iteration":503,"passed_time":8.492987432,"remaining_time":8.358178107},
{"learn":[0.1339240558],"iteration":504,"passed_time":8.507174441,"remaining_time":8.338715541},
{"learn":[0.1337906197],"iteration":505,"passed_time":8.526356315,"remaining_time":8.324150236},
{"learn":[0.1336521451],"iteration":506,"passed_time":8.542711168,"remaining_time":8.306817763},
{"learn":[0.1335226736],"iteration":507,"passed_time":8.560119032,"remaining_time":8.290508983},
{"learn":[0.1333423961],"iteration":508,"passed_time":8.575072861,"remaining_time":8.271828634},
{"learn":[0.1332175962],"iteration":509,"passed_time":8.590874364,"remaining_time":8.25397733},
{"learn":[0.1331477459],"iteration":510,"passed_time":8.605130692,"remaining_time":8.234655398},
{"learn":[0.133033032],"iteration":511,"passed_time":8.621146412,"remaining_time":8.217030173},
{"learn":[0.1329874704],"iteration":512,"passed_time":8.636656531,"remaining_time":8.198931249},
{"learn":[0.1328349452],"iteration":513,"passed_time":8.652998065,"remaining_time":8.181628521},
{"learn":[0.1327280621],"iteration":514,"passed_time":8.671437534,"remaining_time":8.16630525},
{"learn":[0.1326724503],"iteration":515,"passed_time":8.688554581,"remaining_time":8.149729491},
{"learn":[0.1325830186],"iteration":516,"passed_time":8.70610571,"remaining_time":8.133557172},
{"learn":[0.1324987865],"iteration":517,"passed_time":8.720197204,"remaining_time":8.114160333},
{"learn":[0.1324247925],"iteration":518,"passed_time":8.735712194,"remaining_time":8.096103209},
{"learn":[0.1323346896],"iteration":519,"passed_time":8.751870081,"remaining_time":8.078649305},
{"learn":[0.132233203],"iteration":520,"passed_time":8.77032477,"remaining_time":8.063312025},
{"learn":[0.1320812952],"iteration":521,"passed_time":8.785435516,"remaining_time":8.044900722},
{"learn":[0.1320322165],"iteration":522,"passed_time":8.805931507,"remaining_time":8.03141363},
{"learn":[0.1319367082],"iteration":523,"passed_time":8.820653647,"remaining_time":8.01265484},
{"learn":[0.1317779004],"iteration":524,"passed_time":8.834559289,"remaining_time":7.99317269},
{"learn":[0.1316566445],"iteration":525,"passed_time":8.853761313,"remaining_time":7.978484529},
{"learn":[0.1316012833],"iteration":526,"passed_time":8.870431687,"remaining_time":7.961506998},
{"learn":[0.1314502347],"iteration":527,"passed_time":8.884971957,"remaining_time":7.942626446},
{"learn":[0.1313321737],"iteration":528,"passed_time":8.89976623,"remaining_time":7.923988458},
{"learn":[0.1312142023],"iteration":529,"passed_time":8.915863295,"remaining_time":7.90652028},
{"learn":[0.1311328966],"iteration":530,"passed_time":8.931350232,"remaining_time":7.888518378},
{"learn":[0.1310112469],"iteration":531,"passed_time":8.94782075,"remaining_time":7.871391186},
{"learn":[0.1308986451],"iteration":532,"passed_time":8.965706812,"remaining_time":7.855506719},
{"learn":[0.1307504067],"iteration":533,"passed_time":8.982039516,"remaining_time":7.838259203},
{"learn":[0.1306996902],"iteration":534,"passed_time":8.998179133,"remaining_time":7.820847284},
{"learn":[0.1306460652],"iteration":535,"passed_time":9.018091112,"remaining_time":7.806705739},
{"learn":[0.1305423949],"iteration":536,"passed_time":9.033404755,"remaining_time":7.788578029},
{"learn":[0.1304970839],"iteration":537,"passed_time":9.047564659,"remaining_time":7.769470023},
{"learn":[0.1303803833],"iteration":538,"passed_time":9.064868636,"remaining_time":7.753069465},
{"learn":[0.1302543394],"iteration":539,"passed_time":9.084099284,"remaining_time":7.738306797},
{"learn":[0.1301290115],"iteration":540,"passed_time":9.099550686,"remaining_time":7.720321192},
{"learn":[0.130030693],"iteration":541,"passed_time":9.115436326,"remaining_time":7.702711877},
{"learn":[0.1299012931],"iteration":542,"passed_time":9.129958492,"remaining_time":7.683961383},
{"learn":[0.1298474264],"iteration":543,"passed_time":9.145503482,"remaining_time":7.666083801},
{"learn":[0.1297561601],"iteration":544,"passed_time":9.16182937,"remaining_time":7.648866722},
{"learn":[0.1296501182],"iteration":545,"passed_time":9.183294074,"remaining_time":7.635925842},
{"learn":[0.1295352343],"iteration":546,"passed_time":9.20265831,"remaining_time":7.621214286},
{"learn":[0.1294996155],"iteration":547,"passed_time":9.218086395,"remaining_time":7.603239143},
{"learn":[0.1294552084],"iteration":548,"passed_time":9.232605821,"remaining_time":7.584526822},
{"learn":[0.1294093515],"iteration":549,"passed_time":9.247609859,"remaining_time":7.566226248},
{"learn":[0.1292828602],"iteration":550,"passed_time":9.261953882,"remaining_time":7.547399806},
{"learn":[0.1291191929],"iteration":551,"passed_time":9.276645385,"remaining_time":7.528871616},
{"learn":[0.1290390417],"iteration":552,"passed_time":9.295523273,"remaining_time":7.513741235},
{"learn":[0.1289244263],"iteration":553,"passed_time":9.311420214,"remaining_time":7.496197501},
{"learn":[0.1288415366],"iteration":554,"passed_time":9.328465607,"remaining_time":7.479580532},
{"learn":[0.1287079842],"iteration":555,"passed_time":9.346278464,"remaining_time":7.463574889},
{"learn":[0.1285695722],"iteration":556,"passed_time":9.362766176,"remaining_time":7.446508826},
{"learn":[0.1284813129],"iteration":557,"passed_time":9.377759969,"remaining_time":7.428261481},
{"learn":[0.1283467312],"iteration":558,"passed_time":9.395910236,"remaining_time":7.412515946},
{"learn":[0.1282137426],"iteration":559,"passed_time":9.411463161,"remaining_time":7.394721055},
{"learn":[0.1281507833],"iteration":560,"passed_time":9.426328917,"remaining_time":7.376396425},
{"learn":[0.1280447415],"iteration":561,"passed_time":9.440790722,"remaining_time":7.357769282},
{"learn":[0.1279325245],"iteration":562,"passed_time":9.456872511,"remaining_time":7.340414364},
{"learn":[0.127816683],"iteration":563,"passed_time":9.473319549,"remaining_time":7.323346318},
{"learn":[0.1276708877],"iteration":564,"passed_time":9.492047738,"remaining_time":7.308036754},
{"learn":[0.1275825389],"iteration":565,"passed_time":9.509078264,"remaining_time":7.291413369},
{"learn":[0.1274503915],"iteration":566,"passed_time":9.525234006,"remaining_time":7.274120502},
{"learn":[0.1272887378],"iteration":567,"passed_time":9.540000712,"remaining_time":7.255775189},
{"learn":[0.1272202299],"iteration":568,"passed_time":9.555557891,"remaining_time":7.238041215},
{"learn":[0.1270770031],"iteration":569,"passed_time":9.577978935,"remaining_time":7.225492881},
{"learn":[0.1269536441],"iteration":570,"passed_time":9.593326437,"remaining_time":7.207595519},
{"learn":[0.1268432259],"iteration":571,"passed_time":9.611082141,"remaining_time":7.191509015},
{"learn":[0.1266608633],"iteration":572,"passed_time":9.626595856,"remaining_time":7.173745952},
{"learn":[0.1265788327],"iteration":573,"passed_time":9.643405445,"remaining_time":7.156952473},
{"learn":[0.1265045166],"iteration":574,"passed_time":9.665384282,"remaining_time":7.143979686},
{"learn":[0.126416651],"iteration":575,"passed_time":9.690155901,"remaining_time":7.133031427},
{"learn":[0.1262684842],"iteration":576,"passed_time":9.712182538,"remaining_time":7.120022901},
{"learn":[0.1262117805],"iteration":577,"passed_time":9.729154685,"remaining_time":7.103292867},
{"learn":[0.1261094616],"iteration":578,"passed_time":9.745729433,"remaining_time":7.086273042},
{"learn":[0.1260349576],"iteration":579,"passed_time":9.761728871,"remaining_time":7.068838148},
{"learn":[0.125938062],"iteration":580,"passed_time":9.777853599,"remaining_time":7.051498551},
{"learn":[0.125881081],"iteration":581,"passed_time":9.793723528,"remaining_time":7.033980129},
{"learn":[0.1257632437],"iteration":582,"passed_time":9.813351927,"remaining_time":7.019155667},
{"learn":[0.1256688272],"iteration":583,"passed_time":9.834184397,"remaining_time":7.005172447},
{"learn":[0.1255519654],"iteration":584,"passed_time":9.854039297,"remaining_time":6.990472322},
{"learn":[0.1254611645],"iteration":585,"passed_time":9.868802341,"remaining_time":6.972157286},
{"learn":[0.1253819082],"iteration":586,"passed_time":9.884666318,"remaining_time":6.954628942},
{"learn":[0.1253136598],"iteration":587,"passed_time":9.901561698,"remaining_time":6.937828945},
{"learn":[0.1252599632],"iteration":588,"passed_time":9.922005472,"remaining_time":6.923504667},
{"learn":[0.1251997693],"iteration":589,"passed_time":9.936878763,"remaining_time":6.905288632},
{"learn":[0.1251630319],"iteration":590,"passed_time":9.950742599,"remaining_time":6.886385318},
{"learn":[0.1250964033],"iteration":591,"passed_time":9.966522594,"remaining_time":6.868819625},
{"learn":[0.1250533834],"iteration":592,"passed_time":9.982585952,"remaining_time":6.851454439},
{"learn":[0.1249541789],"iteration":593,"passed_time":10.00599833,"remaining_time":6.839116707},
{"learn":[0.1248544553],"iteration":594,"passed_time":10.02275998,"remaining_time":6.822214778},
{"learn":[0.124775575],"iteration":595,"passed_time":10.0378714,"remaining_time":6.804194708},
{"learn":[0.1246650047],"iteration":596,"passed_time":10.05326287,"remaining_time":6.78637343},
{"learn":[0.1246217431],"iteration":597,"passed_time":10.06752308,"remaining_time":6.767799797},
{"learn":[0.1245629901],"iteration":598,"passed_time":10.08189911,"remaining_time":6.749318101},
{"learn":[0.1245217063],"iteration":599,"passed_time":10.09800707,"remaining_time":6.732004715},
{"learn":[0.1243948212],"iteration":600,"passed_time":10.11408875,"remaining_time":6.714677888},
{"learn":[0.124329025],"iteration":601,"passed_time":10.13372806,"remaining_time":6.699707259},
{"learn":[0.1242661641],"iteration":602,"passed_time":10.14797699,"remaining_time":6.681172247},
{"learn":[0.1241494277],"iteration":603,"passed_time":10.16536021,"remaining_time":6.66470636},
{"learn":[0.1240840878],"iteration":604,"passed_time":10.18331947,"remaining_time":6.64861354},
{"learn":[0.1239673156],"iteration":605,"passed_time":10.19775904,"remaining_time":6.630226177},
{"learn":[0.1238632605],"iteration":606,"passed_time":10.21442308,"remaining_time":6.613292046},
{"learn":[0.1237915487],"iteration":607,"passed_time":10.23245324,"remaining_time":6.59723959},
{"learn":[0.1236480265],"iteration":608,"passed_time":10.24776338,"remaining_time":6.579434286},
{"learn":[0.1236093292],"iteration":609,"passed_time":10.26201852,"remaining_time":6.560962661},
{"learn":[0.1235318808],"iteration":610,"passed_time":10.27784416,"remaining_time":6.543504708},
{"learn":[0.1234550051],"iteration":611,"passed_time":10.29422739,"remaining_time":6.526405603},
{"learn":[0.1233462515],"iteration":612,"passed_time":10.30995397,"remaining_time":6.508894269},
{"learn":[0.1232884203],"iteration":613,"passed_time":10.33064992,"remaining_time":6.494512818},
{"learn":[0.1231941022],"iteration":614,"passed_time":10.34690333,"remaining_time":6.477329729},
{"learn":[0.1230994887],"iteration":615,"passed_time":10.3610667,"remaining_time":6.458846774},
{"learn":[0.1229913527],"iteration":616,"passed_time":10.37696357,"remaining_time":6.441453883},
{"learn":[0.122945102],"iteration":617,"passed_time":10.39535512,"remaining_time":6.425607859},
{"learn":[0.1228948241],"iteration":618,"passed_time":10.40969065,"remaining_time":6.40725709},
{"learn":[0.1228089274],"iteration":619,"passed_time":10.42581106,"remaining_time":6.390013229},
{"learn":[0.1227147525],"iteration":620,"passed_time":10.44505558,"remaining_time":6.374679655},
{"learn":[0.1226420383],"iteration":621,"passed_time":10.45927683,"remaining_time":6.356280774},
{"learn":[0.122575186],"iteration":622,"passed_time":10.47532688,"remaining_time":6.339001979},
{"learn":[0.1224798566],"iteration":623,"passed_time":10.49441756,"remaining_time":6.323559298},
{"learn":[0.1223453108],"iteration":624,"passed_time":10.51158612,"remaining_time":6.306951674},
{"learn":[0.1222750398],"iteration":625,"passed_time":10.5300089,"remaining_time":6.291091578},
{"learn":[0.1221928571],"iteration":626,"passed_time":10.54781978,"remaining_time":6.274859294},
{"learn":[0.1220860188],"iteration":627,"passed_time":10.56562892,"remaining_time":6.258620952},
{"learn":[0.121985096],"iteration":628,"passed_time":10.58158342,"remaining_time":6.2412837},
{"learn":[0.1219300927],"iteration":629,"passed_time":10.5965308,"remaining_time":6.223359357},
{"learn":[0.1218737292],"iteration":630,"passed_time":10.61234984,"remaining_time":6.205954187},
{"learn":[0.121784915],"iteration":631,"passed_time":10.62728682,"remaining_time":6.188040427},
{"learn":[0.1217271374],"iteration":632,"passed_time":10.64418761,"remaining_time":6.171274647},
{"learn":[0.121688279],"iteration":633,"passed_time":10.66029806,"remaining_time":6.154052192},
{"learn":[0.1216696104],"iteration":634,"passed_time":10.67681062,"remaining_time":6.13706437},
{"learn":[0.1215675332],"iteration":635,"passed_time":10.69164103,"remaining_time":6.119115306},
{"learn":[0.1214055484],"iteration":636,"passed_time":10.70638083,"remaining_time":6.101124398},
{"learn":[0.1212796566],"iteration":637,"passed_time":10.72261431,"remaining_time":6.083991191},
{"learn":[0.1212431519],"iteration":638,"passed_time":10.73874529,"remaining_time":6.066802893},
{"learn":[0.1211908156],"iteration":639,"passed_time":10.75769411,"remaining_time":6.051202935},
{"learn":[0.1211251804],"iteration":640,"passed_time":10.77635215,"remaining_time":6.035429674},
{"learn":[0.1210242934],"iteration":641,"passed_time":10.79226044,"remaining_time":6.018114077},
{"learn":[0.1209890953],"iteration":642,"passed_time":10.80746165,"remaining_time":6.000410279},
{"learn":[0.1208612615],"iteration":643,"passed_time":10.82518905,"remaining_time":5.984110715},
{"learn":[0.1207606609],"iteration":644,"passed_time":10.84053816,"remaining_time":5.966497745},
{"learn":[0.1206326661],"iteration":645,"passed_time":10.85780329,"remaining_time":5.949941741},
{"learn":[0.1206027123],"iteration":646,"passed_time":10.87264479,"remaining_time":5.932061222},
{"learn":[0.1205689819],"iteration":647,"passed_time":10.88713985,"remaining_time":5.914001896},
{"learn":[0.1204593782],"iteration":648,"passed_time":10.90354079,"remaining_time":5.896984311},
{"learn":[0.1203618114],"iteration":649,"passed_time":10.9203024,"remaining_time":5.880162832},
{"learn":[0.1202897863],"iteration":650,"passed_time":10.93587834,"remaining_time":5.862705902},
{"learn":[0.1201800573],"iteration":651,"passed_time":10.95390555,"remaining_time":5.846563084},
{"learn":[0.12011214],"iteration":652,"passed_time":10.96845443,"remaining_time":5.828566137},
{"learn":[0.1200284449],"iteration":653,"passed_time":10.98711281,"remaining_time":5.812753873},
{"learn":[0.1199243629],"iteration":654,"passed_time":11.00206353,"remaining_time":5.794980029},
{"learn":[0.1198632204],"iteration":655,"passed_time":11.01760221,"remaining_time":5.777523108},
{"learn":[0.1197583509],"iteration":656,"passed_time":11.03341784,"remaining_time":5.760216618},
{"learn":[0.1196104525],"iteration":657,"passed_time":11.04972677,"remaining_time":5.743171058},
{"learn":[0.1195101114],"iteration":658,"passed_time":11.07579204,"remaining_time":5.731176155},
{"learn":[0.1194504992],"iteration":659,"passed_time":11.09505064,"remaining_time":5.71563215},
{"learn":[0.1193994069],"iteration":660,"passed_time":11.11352827,"remaining_time":5.699676373},
{"learn":[0.1193150406],"iteration":661,"passed_time":11.13172852,"remaining_time":5.683571358},
{"learn":[0.1192384334],"iteration":662,"passed_time":11.15500959,"remaining_time":5.670042583},
{"learn":[0.1191428803],"iteration":663,"passed_time":11.17645093,"remaining_time":5.655553483},
{"learn":[0.1190731999],"iteration":664,"passed_time":11.19358403,"remaining_time":5.638873158},
{"learn":[0.1190210695],"iteration":665,"passed_time":11.2092279,"remaining_time":5.621444623},
{"learn":[0.1188750773],"iteration":666,"passed_time":11.22502019,"remaining_time":5.604095537},
{"learn":[0.1188254437],"iteration":667,"passed_time":11.24134187,"remaining_time":5.587014221},
{"learn":[0.118787516],"iteration":668,"passed_time":11.25759119,"remaining_time":5.569899379},
{"learn":[0.1187475121],"iteration":669,"passed_time":11.27332675,"remaining_time":5.552534069},
{"learn":[0.1187001516],"iteration":670,"passed_time":11.29058099,"remaining_time":5.535918249},
{"learn":[0.1186186044],"iteration":671,"passed_time":11.30816333,"remaining_time":5.519460673},
{"learn":[0.118507873],"iteration":672,"passed_time":11.32500943,"remaining_time":5.502642026},
{"learn":[0.1184620787],"iteration":673,"passed_time":11.34071652,"remaining_time":5.48527238},
{"learn":[0.1183647984],"iteration":674,"passed_time":11.35664589,"remaining_time":5.46801469},
{"learn":[0.1183080858],"iteration":675,"passed_time":11.37369341,"remaining_time":5.451296841},
{"learn":[0.1182163272],"iteration":676,"passed_time":11.39121366,"remaining_time":5.434803564},
{"learn":[0.1181146258],"iteration":677,"passed_time":11.40704168,"remaining_time":5.417503571},
{"learn":[0.1180309844],"iteration":678,"passed_time":11.42279029,"remaining_time":5.400170372},
{"learn":[0.1179343931],"iteration":679,"passed_time":11.43894494,"remaining_time":5.383032913},
{"learn":[0.1178447645],"iteration":680,"passed_time":11.45484791,"remaining_time":5.365780444},
{"learn":[0.1177816352],"iteration":681,"passed_time":11.47114144,"remaining_time":5.348714044},
{"learn":[0.1177623939],"iteration":682,"passed_time":11.48933994,"remaining_time":5.332534059},
{"learn":[0.1177424814],"iteration":683,"passed_time":11.50508422,"remaining_time":5.315214348},
{"learn":[0.1175801207],"iteration":684,"passed_time":11.52115792,"remaining_time":5.298050724},
{"learn":[0.1175281871],"iteration":685,"passed_time":11.53753124,"remaining_time":5.28102742},
{"learn":[0.1174008009],"iteration":686,"passed_time":11.5556552,"remaining_time":5.264803605},
{"learn":[0.1173102863],"iteration":687,"passed_time":11.57492308,"remaining_time":5.249093023},
{"learn":[0.1172420647],"iteration":688,"passed_time":11.59304174,"remaining_time":5.232853381},
{"learn":[0.117200781],"iteration":689,"passed_time":11.60946508,"remaining_time":5.21584663},
{"learn":[0.1171637929],"iteration":690,"passed_time":11.62579556,"remaining_time":5.198800042},
{"learn":[0.117131387],"iteration":691,"passed_time":11.64381201,"remaining_time":5.182505924},
{"learn":[0.1170216669],"iteration":692,"passed_time":11.6611579,"remaining_time":5.165909776},
{"learn":[0.1169363251],"iteration":693,"passed_time":11.67610843,"remaining_time":5.1482553},
{"learn":[0.1168206626],"iteration":694,"passed_time":11.69311667,"remaining_time":5.13151163},
{"learn":[0.1168085451],"iteration":695,"passed_time":11.7123377,"remaining_time":5.115733709},
{"learn":[0.116787147],"iteration":696,"passed_time":11.72600589,"remaining_time":5.097531974},
{"learn":[0.1166892043],"iteration":697,"passed_time":11.74137997,"remaining_time":5.080081307},
{"learn":[0.1166407879],"iteration":698,"passed_time":11.75704455,"remaining_time":5.062761673},
{"learn":[0.1165817932],"iteration":699,"passed_time":11.77235306,"remaining_time":5.045294169},
{"learn":[0.1165490651],"iteration":700,"passed_time":11.78841115,"remaining_time":5.028152546},
{"learn":[0.1164462361],"iteration":701,"passed_time":11.80743339,"remaining_time":5.012272293},
{"learn":[0.1163712398],"iteration":702,"passed_time":11.82375824,"remaining_time":4.995243524},
{"learn":[0.1162863633],"iteration":703,"passed_time":11.83943934,"remaining_time":4.977946087},
{"learn":[0.1161960725],"iteration":704,"passed_time":11.85546202,"remaining_time":4.960796165},
{"learn":[0.1161357175],"iteration":705,"passed_time":11.87127491,"remaining_time":4.943562072},
{"learn":[0.1160326468],"iteration":706,"passed_time":11.88752942,"remaining_time":4.926515021},
{"learn":[0.1159422575],"iteration":707,"passed_time":11.9035557,"remaining_time":4.909376078},
{"learn":[0.1159116325],"iteration":708,"passed_time":11.92133444,"remaining_time":4.89295955},
{"learn":[0.1158152471],"iteration":709,"passed_time":11.93748623,"remaining_time":4.875874656},
{"learn":[0.1156629098],"iteration":710,"passed_time":11.95362408,"remaining_time":4.858786723},
{"learn":[0.1155540131],"iteration":711,"passed_time":11.97235246,"remaining_time":4.842749311},
{"learn":[0.1154643666],"iteration":712,"passed_time":11.99350802,"remaining_time":4.827681349},
{"learn":[0.1153731271],"iteration":713,"passed_time":12.00836241,"remaining_time":4.810072339},
{"learn":[0.1152630311],"iteration":714,"passed_time":12.02616428,"remaining_time":4.7936459},
{"learn":[0.1151806605],"iteration":715,"passed_time":12.0414287,"remaining_time":4.776209149},
{"learn":[0.1151416946],"iteration":716,"passed_time":12.05673762,"remaining_time":4.758796018},
{"learn":[0.1150839439],"iteration":717,"passed_time":12.07115515,"remaining_time":4.741038651},
{"learn":[0.1150259068],"iteration":718,"passed_time":12.0868389,"remaining_time":4.723785439},
{"learn":[0.1148972229],"iteration":719,"passed_time":12.10348828,"remaining_time":4.706912108},
{"learn":[0.1148324916],"iteration":720,"passed_time":12.12266546,"remaining_time":4.691017564},
{"learn":[0.1147512307],"iteration":721,"passed_time":12.13949623,"remaining_time":4.674210459},
{"learn":[0.1147261455],"iteration":722,"passed_time":12.15631512,"remaining_time":4.657398737},
{"learn":[0.1146329102],"iteration":723,"passed_time":12.17097085,"remaining_time":4.639762367},
{"learn":[0.1145113142],"iteration":724,"passed_time":12.18545609,"remaining_time":4.622069552},
{"learn":[0.1143866665],"iteration":725,"passed_time":12.2012173,"remaining_time":4.604867134},
{"learn":[0.1143446847],"iteration":726,"passed_time":12.21707965,"remaining_time":4.587706664},
{"learn":[0.1142063353],"iteration":727,"passed_time":12.23581098,"remaining_time":4.571621685},
{"learn":[0.1141888481],"iteration":728,"passed_time":12.25063363,"remaining_time":4.554076425},
{"learn":[0.1141227655],"iteration":729,"passed_time":12.26648504,"remaining_time":4.536919125},
{"learn":[0.1140464895],"iteration":730,"passed_time":12.28408167,"remaining_time":4.520407618},
{"learn":[0.1138995129],"iteration":731,"passed_time":12.3035253,"remaining_time":4.504569372},
{"learn":[0.113795413],"iteration":732,"passed_time":12.32006357,"remaining_time":4.487662991},
{"learn":[0.1137184121],"iteration":733,"passed_time":12.33644362,"remaining_time":4.470700276},
{"learn":[0.1136846727],"iteration":734,"passed_time":12.3512185,"remaining_time":4.453160412},
{"learn":[0.1135987223],"iteration":735,"passed_time":12.36584839,"remaining_time":4.435576053},
{"learn":[0.1134894318],"iteration":736,"passed_time":12.38213064,"remaining_time":4.418589361},
{"learn":[0.1134156437],"iteration":737,"passed_time":12.40156608,"remaining_time":4.402724003},
{"learn":[0.1133474669],"iteration":738,"passed_time":12.41668169,"remaining_time":4.385323303},
{"learn":[0.1132337374],"iteration":739,"passed_time":12.43454272,"remaining_time":4.368893387},
{"learn":[0.1131485567],"iteration":740,"passed_time":12.44886251,"remaining_time":4.351221849},
{"learn":[0.1130360891],"iteration":741,"passed_time":12.46745258,"remaining_time":4.335044157},
{"learn":[0.1129059822],"iteration":742,"passed_time":12.48396449,"remaining_time":4.318141149},
{"learn":[0.1128164879],"iteration":743,"passed_time":12.49764706,"remaining_time":4.300265656},
{"learn":[0.1127584418],"iteration":744,"passed_time":12.51330303,"remaining_time":4.283076876},
{"learn":[0.112692753],"iteration":745,"passed_time":12.53016393,"remaining_time":4.266302465},
{"learn":[0.1126610988],"iteration":746,"passed_time":12.5524816,"remaining_time":4.251375964},
{"learn":[0.1125272868],"iteration":747,"passed_time":12.56873871,"remaining_time":4.234387908},
{"learn":[0.1124518341],"iteration":748,"passed_time":12.58429816,"remaining_time":4.217168009},
{"learn":[0.1123690966],"iteration":749,"passed_time":12.59973486,"remaining_time":4.19991162},
{"learn":[0.1123388207],"iteration":750,"passed_time":12.61481472,"remaining_time":4.182541765},
{"learn":[0.1122398041],"iteration":751,"passed_time":12.63242458,"remaining_time":4.166012363},
{"learn":[0.1121745716],"iteration":752,"passed_time":12.64902201,"remaining_time":4.14914799},
{"learn":[0.1120831532],"iteration":753,"passed_time":12.66471326,"remaining_time":4.131988675},
{"learn":[0.1119786237],"iteration":754,"passed_time":12.67985681,"remaining_time":4.114655521},
{"learn":[0.1119127827],"iteration":755,"passed_time":12.69406688,"remaining_time":4.097026877},
{"learn":[0.1118336339],"iteration":756,"passed_time":12.70857048,"remaining_time":4.079501489},
{"learn":[0.11173008],"iteration":757,"passed_time":12.72433277,"remaining_time":4.062385923},
{"learn":[0.1117103644],"iteration":758,"passed_time":12.74177167,"remaining_time":4.045806287},
{"learn":[0.1116293272],"iteration":759,"passed_time":12.75752346,"remaining_time":4.028691618},
{"learn":[0.1115892338],"iteration":760,"passed_time":12.77347944,"remaining_time":4.01164466},
{"learn":[0.1115141569],"iteration":761,"passed_time":12.79137352,"remaining_time":3.995205902},
{"learn":[0.1114467229],"iteration":762,"passed_time":12.81036858,"remaining_time":3.979105312},
{"learn":[0.1113641017],"iteration":763,"passed_time":12.82713822,"remaining_time":3.962309711},
{"learn":[0.1112934817],"iteration":764,"passed_time":12.84139525,"remaining_time":3.944742332},
{"learn":[0.1112227901],"iteration":765,"passed_time":12.8598465,"remaining_time":3.928464857},
{"learn":[0.1111839675],"iteration":766,"passed_time":12.8738292,"remaining_time":3.910824255},
{"learn":[0.1110896225],"iteration":767,"passed_time":12.89141791,"remaining_time":3.894282495},
{"learn":[0.1110703812],"iteration":768,"passed_time":12.90592051,"remaining_time":3.876810971},
{"learn":[0.1110538427],"iteration":769,"passed_time":12.92230958,"remaining_time":3.859910654},
{"learn":[0.1109539133],"iteration":770,"passed_time":12.93814371,"remaining_time":3.842846835},
{"learn":[0.1108382329],"iteration":771,"passed_time":12.95628198,"remaining_time":3.826466698},
{"learn":[0.1107602296],"iteration":772,"passed_time":12.97361173,"remaining_time":3.809844583},
{"learn":[0.1106758722],"iteration":773,"passed_time":12.990587,"remaining_time":3.793117135},
{"learn":[0.1106612041],"iteration":774,"passed_time":13.00500608,"remaining_time":3.775646925},
{"learn":[0.1105691859],"iteration":775,"passed_time":13.02087442,"remaining_time":3.758602925},
{"learn":[0.110492015],"iteration":776,"passed_time":13.03677461,"remaining_time":3.741571092},
{"learn":[0.1103596528],"iteration":777,"passed_time":13.05264658,"remaining_time":3.724534115},
{"learn":[0.1102709997],"iteration":778,"passed_time":13.0703468,"remaining_time":3.708018798},
{"learn":[0.1101920388],"iteration":779,"passed_time":13.08619244,"remaining_time":3.690977355},
{"learn":[0.110139085],"iteration":780,"passed_time":13.10228709,"remaining_time":3.674008799},
{"learn":[0.1100891382],"iteration":781,"passed_time":13.11813813,"remaining_time":3.656974568},
{"learn":[0.1100196637],"iteration":782,"passed_time":13.13407866,"remaining_time":3.63996816},
{"learn":[0.1099445242],"iteration":783,"passed_time":13.15233245,"remaining_time":3.623601797},
{"learn":[0.1099348499],"iteration":784,"passed_time":13.16932479,"remaining_time":3.606885134},
{"learn":[0.1098571777],"iteration":785,"passed_time":13.19118578,"remaining_time":3.591493328},
{"learn":[0.1097572215],"iteration":786,"passed_time":13.20675613,"remaining_time":3.574382536},
{"learn":[0.1096910404],"iteration":787,"passed_time":13.22213988,"remaining_time":3.557225449},
{"learn":[0.1096712711],"iteration":788,"passed_time":13.23640901,"remaining_time":3.53977478},
{"learn":[0.1095820631],"iteration":789,"passed_time":13.251161,"remaining_time":3.52246052},
{"learn":[0.10949818],"iteration":790,"passed_time":13.27062916,"remaining_time":3.506398855},
{"learn":[0.1094105203],"iteration":791,"passed_time":13.28545824,"remaining_time":3.489110246},
{"learn":[0.1093529486],"iteration":792,"passed_time":13.30030224,"remaining_time":3.471831732},
{"learn":[0.1092593822],"iteration":793,"passed_time":13.32029316,"remaining_time":3.455894698},
{"learn":[0.1091860595],"iteration":794,"passed_time":13.33737564,"remaining_time":3.439197492},
{"learn":[0.1091389318],"iteration":795,"passed_time":13.35296886,"remaining_time":3.422117646},
{"learn":[0.1090690367],"iteration":796,"passed_time":13.36681325,"remaining_time":3.404596097},
{"learn":[0.1089862902],"iteration":797,"passed_time":13.38519043,"remaining_time":3.388231161},
{"learn":[0.1089671294],"iteration":798,"passed_time":13.3991672,"remaining_time":3.370754201},
{"learn":[0.1088386245],"iteration":799,"passed_time":13.4148327,"remaining_time":3.353708176},
{"learn":[0.1087253783],"iteration":800,"passed_time":13.43095384,"remaining_time":3.336778795},
{"learn":[0.1086665626],"iteration":801,"passed_time":13.44696807,"remaining_time":3.319825034},
{"learn":[0.1086399112],"iteration":802,"passed_time":13.46424658,"remaining_time":3.30318378},
{"learn":[0.1085565024],"iteration":803,"passed_time":13.48454489,"remaining_time":3.287277114},
{"learn":[0.1084781949],"iteration":804,"passed_time":13.50096587,"remaining_time":3.270420303},
{"learn":[0.10840259],"iteration":805,"passed_time":13.51801822,"remaining_time":3.253716545},
{"learn":[0.1083694771],"iteration":806,"passed_time":13.53438024,"remaining_time":3.236846822},
{"learn":[0.1083437743],"iteration":807,"passed_time":13.54946462,"remaining_time":3.219674761},
{"learn":[0.108270031],"iteration":808,"passed_time":13.565633,"remaining_time":3.202763786},
{"learn":[0.1081780576],"iteration":809,"passed_time":13.5871291,"remaining_time":3.187104356},
{"learn":[0.1081135411],"iteration":810,"passed_time":13.6027794,"remaining_time":3.170068197},
{"learn":[0.107989502],"iteration":811,"passed_time":13.61913109,"remaining_time":3.153197839},
{"learn":[0.1079245827],"iteration":812,"passed_time":13.63454994,"remaining_time":3.136114193},
{"learn":[0.1078682908],"iteration":813,"passed_time":13.65353627,"remaining_time":3.11984981},
{"learn":[0.1077992727],"iteration":814,"passed_time":13.66939215,"remaining_time":3.102868157},
{"learn":[0.107709143],"iteration":815,"passed_time":13.69003824,"remaining_time":3.086969408},
{"learn":[0.1076266829],"iteration":816,"passed_time":13.70779341,"remaining_time":3.070411498},
{"learn":[0.1075708384],"iteration":817,"passed_time":13.72429652,"remaining_time":3.053572086},
{"learn":[0.1075522414],"iteration":818,"passed_time":13.73989221,"remaining_time":3.036532955},
{"learn":[0.1075274068],"iteration":819,"passed_time":13.75551853,"remaining_time":3.019504067},
{"learn":[0.1074449824],"iteration":820,"passed_time":13.77158652,"remaining_time":3.002574893},
{"learn":[0.10737498],"iteration":821,"passed_time":13.79140662,"remaining_time":2.986460314},
{"learn":[0.1072592011],"iteration":822,"passed_time":13.8093562,"remaining_time":2.969934444},
{"learn":[0.1072055224],"iteration":823,"passed_time":13.82844868,"remaining_time":2.953649233},
{"learn":[0.1071129315],"iteration":824,"passed_time":13.84294837,"remaining_time":2.936382988},
{"learn":[0.1070890813],"iteration":825,"passed_time":13.85823018,"remaining_time":2.919288198},
{"learn":[0.1069828246],"iteration":826,"passed_time":13.87412304,"remaining_time":2.902325619},
{"learn":[0.1068805057],"iteration":827,"passed_time":13.89029527,"remaining_time":2.885423656},
{"learn":[0.106775314],"iteration":828,"passed_time":13.90868604,"remaining_time":2.868981078},
{"learn":[0.1066591682],"iteration":829,"passed_time":13.92446435,"remaining_time":2.851998722},
{"learn":[0.1065902307],"iteration":830,"passed_time":13.93987389,"remaining_time":2.834944269},
{"learn":[0.106502392],"iteration":831,"passed_time":13.95593953,"remaining_time":2.818026252},
{"learn":[0.1064259817],"iteration":832,"passed_time":13.97958542,"remaining_time":2.802629971},
{"learn":[0.1063752205],"iteration":833,"passed_time":13.99510408,"remaining_time":2.785596256},
{"learn":[0.1062952931],"iteration":834,"passed_time":14.01211426,"remaining_time":2.768860902},
{"learn":[0.106204698],"iteration":835,"passed_time":14.02726617,"remaining_time":2.751760349},
{"learn":[0.1061259429],"iteration":836,"passed_time":14.04192836,"remaining_time":2.734569083},
{"learn":[0.1060834152],"iteration":837,"passed_time":14.05636937,"remaining_time":2.717341096},
{"learn":[0.1059872266],"iteration":838,"passed_time":14.07222071,"remaining_time":2.700390386},
{"learn":[0.1059049545],"iteration":839,"passed_time":14.08857754,"remaining_time":2.68353858},
{"learn":[0.1058556341],"iteration":840,"passed_time":14.10894538,"remaining_time":2.667446273},
{"learn":[0.1058362139],"iteration":841,"passed_time":14.12277679,"remaining_time":2.65011726},
{"learn":[0.1058131601],"iteration":842,"passed_time":14.14167056,"remaining_time":2.633739356},
{"learn":[0.1057594098],"iteration":843,"passed_time":14.15652253,"remaining_time":2.61660843},
{"learn":[0.105659722],"iteration":844,"passed_time":14.17098358,"remaining_time":2.59941119},
{"learn":[0.1055902833],"iteration":845,"passed_time":14.18696737,"remaining_time":2.582497606},
{"learn":[0.105539012],"iteration":846,"passed_time":14.20302363,"remaining_time":2.56559931},
{"learn":[0.1054704862],"iteration":847,"passed_time":14.2211735,"remaining_time":2.549078269},
{"learn":[0.1054204946],"iteration":848,"passed_time":14.23666107,"remaining_time":2.532079883},
{"learn":[0.1054007701],"iteration":849,"passed_time":14.25266263,"remaining_time":2.515175758},
{"learn":[0.1053058703],"iteration":850,"passed_time":14.26865243,"remaining_time":2.498271694},
{"learn":[0.1052525137],"iteration":851,"passed_time":14.28453795,"remaining_time":2.481351663},
{"learn":[0.1051753517],"iteration":852,"passed_time":14.30374652,"remaining_time":2.465006727},
{"learn":[0.1051143165],"iteration":853,"passed_time":14.32196594,"remaining_time":2.448485981},
{"learn":[0.1050524491],"iteration":854,"passed_time":14.3356864,"remaining_time":2.431198278},
{"learn":[0.104967501],"iteration":855,"passed_time":14.35143212,"remaining_time":2.414259609},
{"learn":[0.104871572],"iteration":856,"passed_time":14.36739903,"remaining_time":2.397360632},
{"learn":[0.104841654],"iteration":857,"passed_time":14.3852369,"remaining_time":2.380773474},
{"learn":[0.1048198622],"iteration":858,"passed_time":14.40153623,"remaining_time":2.36393086},
{"learn":[0.1047420737],"iteration":859,"passed_time":14.41739253,"remaining_time":2.347017389},
{"learn":[0.1046908471],"iteration":860,"passed_time":14.43500553,"remaining_time":2.330389975},
{"learn":[0.1046277357],"iteration":861,"passed_time":14.44988214,"remaining_time":2.313322199},
{"learn":[0.1045287907],"iteration":862,"passed_time":14.46976159,"remaining_time":2.297053694},
{"learn":[0.1044721855],"iteration":863,"passed_time":14.48575229,"remaining_time":2.280164712},
{"learn":[0.1043902713],"iteration":864,"passed_time":14.50131117,"remaining_time":2.263210414},
{"learn":[0.1043085182],"iteration":865,"passed_time":14.5162811,"remaining_time":2.246168207},
{"learn":[0.1042273737],"iteration":866,"passed_time":14.53398713,"remaining_time":2.229550505},
{"learn":[0.1041520731],"iteration":867,"passed_time":14.5487017,"remaining_time":2.212475373},
{"learn":[0.1040691745],"iteration":868,"passed_time":14.56381446,"remaining_time":2.195465701},
{"learn":[0.1040119339],"iteration":869,"passed_time":14.57957721,"remaining_time":2.178557514},
{"learn":[0.1039453948],"iteration":870,"passed_time":14.5951305,"remaining_time":2.161620936},
{"learn":[0.1039332236],"iteration":871,"passed_time":14.61055006,"remaining_time":2.144667899},
{"learn":[0.1038883332],"iteration":872,"passed_time":14.62950398,"remaining_time":2.128232538},
{"learn":[0.1038451969],"iteration":873,"passed_time":14.64592687,"remaining_time":2.111426528},
{"learn":[0.1037829178],"iteration":874,"passed_time":14.66148445,"remaining_time":2.094497779},
{"learn":[0.1037229924],"iteration":875,"passed_time":14.67724028,"remaining_time":2.077600222},
{"learn":[0.1036340976],"iteration":876,"passed_time":14.6937728,"remaining_time":2.060814201},
{"learn":[0.1035410593],"iteration":877,"passed_time":14.70972066,"remaining_time":2.043947517},
{"learn":[0.1035090203],"iteration":878,"passed_time":14.72546346,"remaining_time":2.027054696},
{"learn":[0.1034756479],"iteration":879,"passed_time":14.77871156,"remaining_time":2.015278849},
{"learn":[0.1033576316],"iteration":880,"passed_time":14.8467753,"remaining_time":2.005410058},
{"learn":[0.1032609867],"iteration":881,"passed_time":14.9175924,"remaining_time":1.995777668},
{"learn":[0.1032042383],"iteration":882,"passed_time":14.98796747,"remaining_time":1.985948125},
{"learn":[0.1031367954],"iteration":883,"passed_time":15.01607141,"remaining_time":1.97043471},
{"learn":[0.1031186638],"iteration":884,"passed_time":15.05005392,"remaining_time":1.955656724},
{"learn":[0.1030378504],"iteration":885,"passed_time":15.07402663,"remaining_time":1.939547445},
{"learn":[0.1029431654],"iteration":886,"passed_time":15.09951071,"remaining_time":1.923612977},
{"learn":[0.1028842602],"iteration":887,"passed_time":15.12339598,"remaining_time":1.907455348},
{"learn":[0.1028217215],"iteration":888,"passed_time":15.14860737,"remaining_time":1.891445914},
{"learn":[0.1027577688],"iteration":889,"passed_time":15.17217327,"remaining_time":1.875212426},
{"learn":[0.1027143462],"iteration":890,"passed_time":15.19789946,"remaining_time":1.859226757},
{"learn":[0.102668525],"iteration":891,"passed_time":15.22028992,"remaining_time":1.842815371},
{"learn":[0.1026043397],"iteration":892,"passed_time":15.24728619,"remaining_time":1.826942466},
{"learn":[0.1025243496],"iteration":893,"passed_time":15.27230467,"remaining_time":1.810810174},
{"learn":[0.1024972507],"iteration":894,"passed_time":15.29873393,"remaining_time":1.794823534},
{"learn":[0.1024389989],"iteration":895,"passed_time":15.32176666,"remaining_time":1.778419344},
{"learn":[0.1023825548],"iteration":896,"passed_time":15.34767853,"remaining_time":1.762330979},
{"learn":[0.1022873864],"iteration":897,"passed_time":15.37019975,"remaining_time":1.745835607},
{"learn":[0.1022337525],"iteration":898,"passed_time":15.39606606,"remaining_time":1.729702638},
{"learn":[0.1022117906],"iteration":899,"passed_time":15.41959096,"remaining_time":1.713287884},
{"learn":[0.1021631862],"iteration":900,"passed_time":15.44484061,"remaining_time":1.69704686},
{"learn":[0.1021158079],"iteration":901,"passed_time":15.46883168,"remaining_time":1.680649119},
{"learn":[0.1020252933],"iteration":902,"passed_time":15.49924843,"remaining_time":1.664924803},
{"learn":[0.1019345818],"iteration":903,"passed_time":15.53888551,"remaining_time":1.650147134},
{"learn":[0.101913828],"iteration":904,"passed_time":15.5877374,"remaining_time":1.636281826},
{"learn":[0.1018251123],"iteration":905,"passed_time":15.6315689,"remaining_time":1.621818406},
{"learn":[0.1017373899],"iteration":906,"passed_time":15.6796193,"remaining_time":1.607722817},
{"learn":[0.1016650963],"iteration":907,"passed_time":15.72183535,"remaining_time":1.592961291},
{"learn":[0.1015994254],"iteration":908,"passed_time":15.82056852,"remaining_time":1.583797288},
{"learn":[0.1015105575],"iteration":909,"passed_time":15.88898104,"remaining_time":1.571437685},
{"learn":[0.101399128],"iteration":910,"passed_time":15.94835144,"remaining_time":1.558071656},
{"learn":[0.101379305],"iteration":911,"passed_time":15.97866395,"remaining_time":1.541800907},
{"learn":[0.1013635451],"iteration":912,"passed_time":16.00208198,"remaining_time":1.524842423},
{"learn":[0.1013440085],"iteration":913,"passed_time":16.02820813,"remaining_time":1.508124616},
{"learn":[0.1012811208],"iteration":914,"passed_time":16.06023864,"remaining_time":1.491934737},
{"learn":[0.1012409468],"iteration":915,"passed_time":16.08493386,"remaining_time":1.475037602},
{"learn":[0.1012219023],"iteration":916,"passed_time":16.11391418,"remaining_time":1.458511316},
{"learn":[0.1011538777],"iteration":917,"passed_time":16.1326571,"remaining_time":1.441043444},
{"learn":[0.1010673187],"iteration":918,"passed_time":16.15080673,"remaining_time":1.423520506},
{"learn":[0.100977887],"iteration":919,"passed_time":16.16928217,"remaining_time":1.406024537},
{"learn":[0.1009540278],"iteration":920,"passed_time":16.19005694,"remaining_time":1.388723668},
{"learn":[0.1008930106],"iteration":921,"passed_time":16.20729352,"remaining_time":1.371115938},
{"learn":[0.1008514494],"iteration":922,"passed_time":16.22643657,"remaining_time":1.353668056},
{"learn":[0.1008273575],"iteration":923,"passed_time":16.24455642,"remaining_time":1.336132347},
{"learn":[0.1007782967],"iteration":924,"passed_time":16.26269513,"remaining_time":1.318596903},
{"learn":[0.1007374873],"iteration":925,"passed_time":16.28189352,"remaining_time":1.301144839},
{"learn":[0.1006947805],"iteration":926,"passed_time":16.31856685,"remaining_time":1.285065135},
{"learn":[0.1006275882],"iteration":927,"passed_time":16.34543885,"remaining_time":1.268180601},
{"learn":[0.1005996391],"iteration":928,"passed_time":16.37344208,"remaining_time":1.25136102},
{"learn":[0.1005161856],"iteration":929,"passed_time":16.41024008,"remaining_time":1.23517936},
{"learn":[0.100458775],"iteration":930,"passed_time":16.44467035,"remaining_time":1.218777931},
{"learn":[0.1004004694],"iteration":931,"passed_time":16.47454197,"remaining_time":1.202005208},
{"learn":[0.1003882266],"iteration":932,"passed_time":16.49977278,"remaining_time":1.184871143},
{"learn":[0.1003330264],"iteration":933,"passed_time":16.52081422,"remaining_time":1.167423703},
{"learn":[0.1002944902],"iteration":934,"passed_time":16.54104419,"remaining_time":1.149912163},
{"learn":[0.1002326048],"iteration":935,"passed_time":16.56166742,"remaining_time":1.132421704},
{"learn":[0.1001371591],"iteration":936,"passed_time":16.57848481,"remaining_time":1.114668669},
{"learn":[0.1000666017],"iteration":937,"passed_time":16.59463912,"remaining_time":1.096873801},
{"learn":[0.09998918908],"iteration":938,"passed_time":16.61130312,"remaining_time":1.079115538},
{"learn":[0.0999063173],"iteration":939,"passed_time":16.6292453,"remaining_time":1.061441189},
{"learn":[0.09985700591],"iteration":940,"passed_time":16.64560261,"remaining_time":1.043666901},
{"learn":[0.09979255206],"iteration":941,"passed_time":16.66427311,"remaining_time":1.026038047},
{"learn":[0.09970504448],"iteration":942,"passed_time":16.68152988,"remaining_time":1.00832153},
{"learn":[0.09968059461],"iteration":943,"passed_time":16.69747639,"remaining_time":0.9905282603},
{"learn":[0.09966170235],"iteration":944,"passed_time":16.71362711,"remaining_time":0.9727507842},
{"learn":[0.09963518517],"iteration":945,"passed_time":16.73113598,"remaining_time":0.9550542736},
{"learn":[0.0995513737],"iteration":946,"passed_time":16.74700324,"remaining_time":0.937266285},
{"learn":[0.09950040666],"iteration":947,"passed_time":16.76310645,"remaining_time":0.9194952904},
{"learn":[0.09943644504],"iteration":948,"passed_time":16.78033775,"remaining_time":0.9017884354},
{"learn":[0.09939922433],"iteration":949,"passed_time":16.79622436,"remaining_time":0.8840118083},
{"learn":[0.09933002729],"iteration":950,"passed_time":16.81219444,"remaining_time":0.8662434568},
{"learn":[0.09926977969],"iteration":951,"passed_time":16.83174326,"remaining_time":0.8486593238},
{"learn":[0.09921159045],"iteration":952,"passed_time":16.84865244,"remaining_time":0.8309408865},
{"learn":[0.09916521447],"iteration":953,"passed_time":16.86313292,"remaining_time":0.8131070381},
{"learn":[0.09908030222],"iteration":954,"passed_time":16.87985529,"remaining_time":0.7953858514},
{"learn":[0.09902136123],"iteration":955,"passed_time":16.89866538,"remaining_time":0.7777628419},
{"learn":[0.09895673735],"iteration":956,"passed_time":16.9146772,"remaining_time":0.760011619},
{"learn":[0.09889993528],"iteration":957,"passed_time":16.93206138,"remaining_time":0.7423241943},
{"learn":[0.09888092667],"iteration":958,"passed_time":16.9476037,"remaining_time":0.7245586568},
{"learn":[0.09883583941],"iteration":959,"passed_time":16.9637457,"remaining_time":0.7068227377},
{"learn":[0.09879379496],"iteration":960,"passed_time":16.97971671,"remaining_time":0.6890831963},
{"learn":[0.09871324108],"iteration":961,"passed_time":16.9978623,"remaining_time":0.67143323},
{"learn":[0.098640688],"iteration":962,"passed_time":17.01425739,"remaining_time":0.6537149776},
{"learn":[0.09855529248],"iteration":963,"passed_time":17.02997837,"remaining_time":0.635974296},
{"learn":[0.09854197572],"iteration":964,"passed_time":17.0472418,"remaining_time":0.6182937441},
{"learn":[0.0984938546],"iteration":965,"passed_time":17.06363232,"remaining_time":0.6005833322},
{"learn":[0.09842241125],"iteration":966,"passed_time":17.08001731,"remaining_time":0.5828754615},
{"learn":[0.09838434035],"iteration":967,"passed_time":17.0955572,"remaining_time":0.5651423866},
{"learn":[0.09834033597],"iteration":968,"passed_time":17.11139457,"remaining_time":0.5474233556},
{"learn":[0.09824621475],"iteration":969,"passed_time":17.12710412,"remaining_time":0.5297042512},
{"learn":[0.09818462473],"iteration":970,"passed_time":17.14475744,"remaining_time":0.5120473387},
{"learn":[0.09812373276],"iteration":971,"passed_time":17.16133824,"remaining_time":0.4943595379},
{"learn":[0.09807989842],"iteration":972,"passed_time":17.17712835,"remaining_time":0.4766520714},
{"learn":[0.09802055471],"iteration":973,"passed_time":17.19275795,"remaining_time":0.4589442575},
{"learn":[0.09796224018],"iteration":974,"passed_time":17.20682335,"remaining_time":0.4412005987},
{"learn":[0.09791562257],"iteration":975,"passed_time":17.22113556,"remaining_time":0.4234705466},
{"learn":[0.09786233762],"iteration":976,"passed_time":17.23684013,"remaining_time":0.4057802692},
{"learn":[0.09778874641],"iteration":977,"passed_time":17.25466926,"remaining_time":0.3881418444},
{"learn":[0.09773423539],"iteration":978,"passed_time":17.27087146,"remaining_time":0.3704681315},
{"learn":[0.09767740647],"iteration":979,"passed_time":17.28646635,"remaining_time":0.3527850276},
{"learn":[0.09765727024],"iteration":980,"passed_time":17.30826901,"remaining_time":0.335226413},
{"learn":[0.09763136162],"iteration":981,"passed_time":17.32334807,"remaining_time":0.3175359116},
{"learn":[0.09759389033],"iteration":982,"passed_time":17.34199135,"remaining_time":0.2999123631},
{"learn":[0.09751087536],"iteration":983,"passed_time":17.35906466,"remaining_time":0.2822612139},
{"learn":[0.09742363625],"iteration":984,"passed_time":17.37449432,"remaining_time":0.2645862079},
{"learn":[0.09737625793],"iteration":985,"passed_time":17.39095313,"remaining_time":0.2469303689},
{"learn":[0.09729216903],"iteration":986,"passed_time":17.4067351,"remaining_time":0.2292680409},
{"learn":[0.09727871803],"iteration":987,"passed_time":17.4219439,"remaining_time":0.2116025575},
{"learn":[0.09726085495],"iteration":988,"passed_time":17.43872129,"remaining_time":0.1939594886},
{"learn":[0.09723899148],"iteration":989,"passed_time":17.45586837,"remaining_time":0.1763219027},
{"learn":[0.09723186773],"iteration":990,"passed_time":17.4721364,"remaining_time":0.1586773235},
{"learn":[0.09715241463],"iteration":991,"passed_time":17.49016728,"remaining_time":0.1410497361},
{"learn":[0.09704747354],"iteration":992,"passed_time":17.50904314,"remaining_time":0.123427293},
{"learn":[0.09698605356],"iteration":993,"passed_time":17.52551862,"remaining_time":0.1057878387},
{"learn":[0.09696517452],"iteration":994,"passed_time":17.54170641,"remaining_time":0.08814927843},
{"learn":[0.09691011759],"iteration":995,"passed_time":17.55856962,"remaining_time":0.07051634385},
{"learn":[0.09685305598],"iteration":996,"passed_time":17.57545756,"remaining_time":0.05288502775},
{"learn":[0.09678731342],"iteration":997,"passed_time":17.5920948,"remaining_time":0.035254699},
{"learn":[0.09673039501],"iteration":998,"passed_time":17.60765316,"remaining_time":0.01762527843},
{"learn":[0.09664985008],"iteration":999,"passed_time":17.62310375,"remaining_time":0}
]}